Workbook

Sheet Параметры
A1: ВХОДНЫЕ ПАРАМЕТРЫ ПРОЕКТА
A2: Название проекта | C2: Sklad_160
A3: Дата начала строительства | B3: ГГГГ-ММ | C3: 2026-07
A4: Площадь объекта | B4: кв.м. | C4: 3000
A5: Себестоимость строительства (с НДС) | B5: руб. | C5: 150000000
A6: Доля кредита | C6: 0.6
A7: Арендная ставка | B7: руб./кв.м./мес. | C7: 950.4
A8: Годовая инфляция (индексация аренды) | C8: 0.08
A9: Ставка ЦБ (ставка дисконтирования) | C9: 0.14
A10: Кредитная ставка | C10: 0.15
A11: Срок строительства | B11: мес. | C11: 10
A12: Горизонт планирования | B12: мес. | C12: 200
A13: Ставка НДС | C13: 0.2
A14: Ставка налога на прибыль | C14: 0.2
A15: Ставка налога на имущество | B15: в год | C15: 0.022
A16: Операционные расходы | B16: % от выручки б/НДС | C16: 0.15
A17: Срок полезного использования | B17: лет | C17: 40
A18: РАСЧЁТНЫЕ (ПРОИЗВОДНЫЕ) ПАРАМЕТРЫ
A19: Изменяйте только синие ячейки выше — формулы ниже пересчитаются автоматически.
A20: Себестоимость без НДС | B20: руб. | C20: =C5/(1+C13) -> 125000000
A21: НДС строительства | B21: руб. | C21: =C5-C20 -> 25000000
A22: Сумма кредита | B22: руб. | C22: =C5*C6 -> 90000000
A23: Собственные средства | B23: руб. | C23: =C5*(1-C6) -> 60000000
A24: Стоимость 1 кв.м. | B24: руб. | C24: =C5/C4 -> 50000
A25: Период эксплуатации | B25: мес. | C25: =C12-C11 -> 190
A26: Аннуитетный платёж (в мес.) | B26: руб./мес. | C26: =-PMT(C10/12,C12-C11,C5*C6) -> 1242262
A27: Амортизация (в мес.) | B27: руб./мес. | C27: =C20/(C17*12) -> 260416.67
A28: НДС к возмещению (1-3 мес. экспл.) | B28: руб./мес. | C28: =(C5-C5/(1+C13))/3 -> 8333333.3

Sheet Денежные потоки
A1: Мес. | B1: Дата | C1: Фаза | D1: Выручка с НДС | E1: Выручка без НДС | F1: НДС выходной | G1: НДС входной | H1: НДС нетто | I1: Опер. расходы | J1: Амортизация | K1: Налог на имущ. | L1: EBIT | M1: Проценты | N1: EBT | O1: Налог на прибыль | P1: Чистая прибыль | Q1: Капвложения | R1: Транш кредита | S1: Погашение кредита | T1: Остаток кредита | U1: CF инвестора | V1: Накопл. CF
A2: 1 | B2: 2026-08 | C2: Строительство | D2: 0 | E2: 0 | F2: 0 | G2: 0 | H2: 0 | I2: 0 | J2: 0 | K2: 0 | L2: 0 | M2: =T2*Параметры!$C$10/12 -> 112500 | N2: =-M2 -> -112500 | O2: 0 | P2: 0 | Q2: =Параметры!$C$5/Параметры!$C$11 -> 15000000 | R2: =Параметры!$C$22/Параметры!$C$11 -> 9000000 | S2: 0 | T2: =Параметры!$C$22/Параметры!$C$11*A2 -> 9000000 | U2: =-(Параметры!$C$23/Параметры!$C$11+M2) -> -6112500 | V2: =U2 -> -6112500
A3: 2 | B3: 2026-09 | C3: Строительство | D3: 0 | E3: 0 | F3: 0 | G3: 0 | H3: 0 | I3: 0 | J3: 0 | K3: 0 | L3: 0 | M3: =T3*Параметры!$C$10/12 -> 225000 | N3: =-M3 -> -225000 | O3: 0 | P3: 0 | Q3: =Параметры!$C$5/Параметры!$C$11 -> 15000000 | R3: =Параметры!$C$22/Параметры!$C$11 -> 9000000 | S3: 0 | T3: =Параметры!$C$22/Параметры!$C$11*A3 -> 18000000 | U3: =-(Параметры!$C$23/Параметры!$C$11+M3) -> -6225000 | V3: =V2+U3 -> -12337500
A4: 3 | B4: 2026-10 | C4: Строительство | D4: 0 | E4: 0 | F4: 0 | G4: 0 | H4: 0 | I4: 0 | J4: 0 | K4: 0 | L4: 0 | M4: =T4*Параметры!$C$10/12 -> 337500 | N4: =-M4 -> -337500 | O4: 0 | P4: 0 | Q4: =Параметры!$C$5/Параметры!$C$11 -> 15000000 | R4: =Параметры!$C$22/Параметры!$C$11 -> 9000000 | S4: 0 | T4: =Параметры!$C$22/Параметры!$C$11*A4 -> 27000000 | U4: =-(Параметры!$C$23/Параметры!$C$11+M4) -> -6337500 | V4: =V3+U4 -> -18675000
A5: 4 | B5: 2026-11 | C5: Строительство | D5: 0 | E5: 0 | F5: 0 | G5: 0 | H5: 0 | I5: 0 | J5: 0 | K5: 0 | L5: 0 | M5: =T5*Параметры!$C$10/12 -> 450000 | N5: =-M5 -> -450000 | O5: 0 | P5: 0 | Q5: =Параметры!$C$5/Параметры!$C$11 -> 15000000 | R5: =Параметры!$C$22/Параметры!$C$11 -> 9000000 | S5: 0 | T5: =Параметры!$C$22/Параметры!$C$11*A5 -> 36000000 | U5: =-(Параметры!$C$23/Параметры!$C$11+M5) -> -6450000 | V5: =V4+U5 -> -25125000
A6: 5 | B6: 2026-12 | C6: Строительство | D6: 0 | E6: 0 | F6: 0 | G6: 0 | H6: 0 | I6: 0 | J6: 0 | K6: 0 | L6: 0 | M6: =T6*Параметры!$C$10/12 -> 562500 | N6: =-M6 -> -562500 | O6: 0 | P6: 0 | Q6: =Параметры!$C$5/Параметры!$C$11 -> 15000000 | R6: =Параметры!$C$22/Параметры!$C$11 -> 9000000 | S6: 0 | T6: =Параметры!$C$22/Параметры!$C$11*A6 -> 45000000 | U6: =-(Параметры!$C$23/Параметры!$C$11+M6) -> -6562500 | V6: =V5+U6 -> -31687500
A7: 6 | B7: 2027-01 | C7: Строительство | D7: 0 | E7: 0 | F7: 0 | G7: 0 | H7: 0 | I7: 0 | J7: 0 | K7: 0 | L7: 0 | M7: =T7*Параметры!$C$10/12 -> 675000 | N7: =-M7 -> -675000 | O7: 0 | P7: 0 | Q7: =Параметры!$C$5/Параметры!$C$11 -> 15000000 | R7: =Параметры!$C$22/Параметры!$C$11 -> 9000000 | S7: 0 | T7: =Параметры!$C$22/Параметры!$C$11*A7 -> 54000000 | U7: =-(Параметры!$C$23/Параметры!$C$11+M7) -> -6675000 | V7: =V6+U7 -> -38362500
A8: 7 | B8: 2027-02 | C8: Строительство | D8: 0 | E8: 0 | F8: 0 | G8: 0 | H8: 0 | I8: 0 | J8: 0 | K8: 0 | L8: 0 | M8: =T8*Параметры!$C$10/12 -> 787500 | N8: =-M8 -> -787500 | O8: 0 | P8: 0 | Q8: =Параметры!$C$5/Параметры!$C$11 -> 15000000 | R8: =Параметры!$C$22/Параметры!$C$11 -> 9000000 | S8: 0 | T8: =Параметры!$C$22/Параметры!$C$11*A8 -> 63000000 | U8: =-(Параметры!$C$23/Параметры!$C$11+M8) -> -6787500 | V8: =V7+U8 -> -45150000
A9: 8 | B9: 2027-03 | C9: Строительство | D9: 0 | E9: 0 | F9: 0 | G9: 0 | H9: 0 | I9: 0 | J9: 0 | K9: 0 | L9: 0 | M9: =T9*Параметры!$C$10/12 -> 900000 | N9: =-M9 -> -900000 | O9: 0 | P9: 0 | Q9: =Параметры!$C$5/Параметры!$C$11 -> 15000000 | R9: =Параметры!$C$22/Параметры!$C$11 -> 9000000 | S9: 0 | T9: =Параметры!$C$22/Параметры!$C$11*A9 -> 72000000 | U9: =-(Параметры!$C$23/Параметры!$C$11+M9) -> -6900000 | V9: =V8+U9 -> -52050000
A10: 9 | B10: 2027-04 | C10: Строительство | D10: 0 | E10: 0 | F10: 0 | G10: 0 | H10: 0 | I10: 0 | J10: 0 | K10: 0 | L10: 0 | M10: =T10*Параметры!$C$10/12 -> 1012500 | N10: =-M10 -> -1012500 | O10: 0 | P10: 0 | Q10: =Параметры!$C$5/Параметры!$C$11 -> 15000000 | R10: =Параметры!$C$22/Параметры!$C$11 -> 9000000 | S10: 0 | T10: =Параметры!$C$22/Параметры!$C$11*A10 -> 81000000 | U10: =-(Параметры!$C$23/Параметры!$C$11+M10) -> -7012500 | V10: =V9+U10 -> -59062500
A11: 10 | B11: 2027-05 | C11: Строительство | D11: 0 | E11: 0 | F11: 0 | G11: 0 | H11: 0 | I11: 0 | J11: 0 | K11: 0 | L11: 0 | M11: =T11*Параметры!$C$10/12 -> 1125000 | N11: =-M11 -> -1125000 | O11: 0 | P11: 0 | Q11: =Параметры!$C$5/Параметры!$C$11 -> 15000000 | R11: =Параметры!$C$22/Параметры!$C$11 -> 9000000 | S11: 0 | T11: =Параметры!$C$22/Параметры!$C$11*A11 -> 90000000 | U11: =-(Параметры!$C$23/Параметры!$C$11+M11) -> -7125000 | V11: =V10+U11 -> -66187500
A12: 11 | B12: 2027-06 | C12: Эксплуатация | D12: =Параметры!$C$4*Параметры!$C$7*(1+Параметры!$C$8)^INT((A12-Параметры!$C$11-1)/12) -> 2851200 | E12: =D12/(1+Параметры!$C$13) -> 2376000 | F12: =D12-E12 -> 475200 | G12: =IF(AND(A12>Параметры!$C$11,A12<=Параметры!$C$11+3),Параметры!$C$28,0) -> 8333333.3 | H12: =F12-G12 -> -7858133.3 | I12: =E12*Параметры!$C$16 -> 356400 | J12: =Параметры!$C$27 -> 260416.67 | K12: =MAX(0,Параметры!$C$20-Параметры!$C$27*MAX(0,A12-Параметры!$C$11-1))*Параметры!$C$15/12 -> 229166.67 | L12: =E12-I12-J12-K12 -> 1530016.7 | M12: =T11*Параметры!$C$10/12 -> 1125000 | N12: =L12-M12 -> 405016.67 | O12: =MAX(0,N12*Параметры!$C$14) -> 81003.333 | P12: =N12-O12 -> 324013.33 | Q12: 0 | R12: 0 | S12: =MAX(0,MIN(Параметры!$C$26-M12,T11)) -> 117261.95 | T12: =MAX(0,T11-S12) -> 89882738 | U12: =P12+J12-S12-H12 -> 8325301.4 | V12: =V11+U12 -> -57862199
A13: 12 | B13: 2027-07 | C13: Эксплуатация | D13: =Параметры!$C$4*Параметры!$C$7*(1+Параметры!$C$8)^INT((A13-Параметры!$C$11-1)/12) -> 2851200 | E13: =D13/(1+Параметры!$C$13) -> 2376000 | F13: =D13-E13 -> 475200 | G13: =IF(AND(A13>Параметры!$C$11,A13<=Параметры!$C$11+3),Параметры!$C$28,0) -> 8333333.3 | H13: =F13-G13 -> -7858133.3 | I13: =E13*Параметры!$C$16 -> 356400 | J13: =Параметры!$C$27 -> 260416.67 | K13: =MAX(0,Параметры!$C$20-Параметры!$C$27*MAX(0,A13-Параметры!$C$11-1))*Параметры!$C$15/12 -> 228689.24 | L13: =E13-I13-J13-K13 -> 1530494.1 | M13: =T12*Параметры!$C$10/12 -> 1123534.2 | N13: =L13-M13 -> 406959.87 | O13: =MAX(0,N13*Параметры!$C$14) -> 81391.974 | P13: =N13-O13 -> 325567.9 | Q13: 0 | R13: 0 | S13: =MAX(0,MIN(Параметры!$C$26-M13,T12)) -> 118727.73 | T13: =MAX(0,T12-S13) -> 89764010 | U13: =P13+J13-S13-H13 -> 8325390.2 | V13: =V12+U13 -> -49536808
A14: 13 | B14: 2027-08 | C14: Эксплуатация | D14: =Параметры!$C$4*Параметры!$C$7*(1+Параметры!$C$8)^INT((A14-Параметры!$C$11-1)/12) -> 2851200 | E14: =D14/(1+Параметры!$C$13) -> 2376000 | F14: =D14-E14 -> 475200 | G14: =IF(AND(A14>Параметры!$C$11,A14<=Параметры!$C$11+3),Параметры!$C$28,0) -> 8333333.3 | H14: =F14-G14 -> -7858133.3 | I14: =E14*Параметры!$C$16 -> 356400 | J14: =Параметры!$C$27 -> 260416.67 | K14: =MAX(0,Параметры!$C$20-Параметры!$C$27*MAX(0,A14-Параметры!$C$11-1))*Параметры!$C$15/12 -> 228211.81 | L14: =E14-I14-J14-K14 -> 1530971.5 | M14: =T13*Параметры!$C$10/12 -> 1122050.1 | N14: =L14-M14 -> 408921.4 | O14: =MAX(0,N14*Параметры!$C$14) -> 81784.28 | P14: =N14-O14 -> 327137.12 | Q14: 0 | R14: 0 | S14: =MAX(0,MIN(Параметры!$C$26-M14,T13)) -> 120211.82 | T14: =MAX(0,T13-S14) -> 89643798 | U14: =P14+J14-S14-H14 -> 8325475.3 | V14: =V13+U14 -> -41211333
A15: 14 | B15: 2027-09 | C15: Эксплуатация | D15: =Параметры!$C$4*Параметры!$C$7*(1+Параметры!$C$8)^INT((A15-Параметры!$C$11-1)/12) -> 2851200 | E15: =D15/(1+Параметры!$C$13) -> 2376000 | F15: =D15-E15 -> 475200 | G15: =IF(AND(A15>Параметры!$C$11,A15<=Параметры!$C$11+3),Параметры!$C$28,0) -> 0 | H15: =F15-G15 -> 475200 | I15: =E15*Параметры!$C$16 -> 356400 | J15: =Параметры!$C$27 -> 260416.67 | K15: =MAX(0,Параметры!$C$20-Параметры!$C$27*MAX(0,A15-Параметры!$C$11-1))*Параметры!$C$15/12 -> 227734.38 | L15: =E15-I15-J15-K15 -> 1531449 | M15: =T14*Параметры!$C$10/12 -> 1120547.5 | N15: =L15-M15 -> 410901.48 | O15: =MAX(0,N15*Параметры!$C$14) -> 82180.295 | P15: =N15-O15 -> 328721.18 | Q15: 0 | R15: 0 | S15: =MAX(0,MIN(Параметры!$C$26-M15,T14)) -> 121714.47 | T15: =MAX(0,T14-S15) -> 89522084 | U15: =P15+J15-S15-H15 -> -7776.6242 | V15: =V14+U15 -> -41219110
A16: 15 | B16: 2027-10 | C16: Эксплуатация | D16: =Параметры!$C$4*Параметры!$C$7*(1+Параметры!$C$8)^INT((A16-Параметры!$C$11-1)/12) -> 2851200 | E16: =D16/(1+Параметры!$C$13) -> 2376000 | F16: =D16-E16 -> 475200 | G16: =IF(AND(A16>Параметры!$C$11,A16<=Параметры!$C$11+3),Параметры!$C$28,0) -> 0 | H16: =F16-G16 -> 475200 | I16: =E16*Параметры!$C$16 -> 356400 | J16: =Параметры!$C$27 -> 260416.67 | K16: =MAX(0,Параметры!$C$20-Параметры!$C$27*MAX(0,A16-Параметры!$C$11-1))*Параметры!$C$15/12 -> 227256.94 | L16: =E16-I16-J16-K16 -> 1531926.4 | M16: =T15*Параметры!$C$10/12 -> 1119026.1 | N16: =L16-M16 -> 412900.34 | O16: =MAX(0,N16*Параметры!$C$14) -> 82580.068 | P16: =N16-O16 -> 330320.27 | Q16: 0 | R16: 0 | S16: =MAX(0,MIN(Параметры!$C$26-M16,T15)) -> 123235.9 | T16: =MAX(0,T15-S16) -> 89398848 | U16: =P16+J16-S16-H16 -> -7698.966 | V16: =V15+U16 -> -41226809
A17: 16 | B17: 2027-11 | C17: Эксплуатация | D17: =Параметры!$C$4*Параметры!$C$7*(1+Параметры!$C$8)^INT((A17-Параметры!$C$11-1)/12) -> 2851200 | E17: =D17/(1+Параметры!$C$13) -> 2376000 | F17: =D17-E17 -> 475200 | G17: =IF(AND(A17>Параметры!$C$11,A17<=Параметры!$C$11+3),Параметры!$C$28,0) -> 0 | H17: =F17-G17 -> 475200 | I17: =E17*Параметры!$C$16 -> 356400 | J17: =Параметры!$C$27 -> 260416.67 | K17: =MAX(0,Параметры!$C$20-Параметры!$C$27*MAX(0,A17-Параметры!$C$11-1))*Параметры!$C$15/12 -> 226779.51 | L17: =E17-I17-J17-K17 -> 1532403.8 | M17: =T16*Параметры!$C$10/12 -> 1117485.6 | N17: =L17-M17 -> 414918.22 | O17: =MAX(0,N17*Параметры!$C$14) -> 82983.644 | P17: =N17-O17 -> 331934.57 | Q17: 0 | R17: 0 | S17: =MAX(0,MIN(Параметры!$C$26-M17,T16)) -> 124776.35 | T17: =MAX(0,T16-S17) -> 89274072 | U17: =P17+J17-S17-H17 -> -7625.1113 | V17: =V16+U17 -> -41234434
A18: 17 | B18: 2027-12 | C18: Эксплуатация | D18: =Параметры!$C$4*Параметры!$C$7*(1+Параметры!$C$8)^INT((A18-Параметры!$C$11-1)/12) -> 2851200 | E18: =D18/(1+Параметры!$C$13) -> 2376000 | F18: =D18-E18 -> 475200 | G18: =IF(AND(A18>Параметры!$C$11,A18<=Параметры!$C$11+3),Параметры!$C$28,0) -> 0 | H18: =F18-G18 -> 475200 | I18: =E18*Параметры!$C$16 -> 356400 | J18: =Параметры!$C$27 -> 260416.67 | K18: =MAX(0,Параметры!$C$20-Параметры!$C$27*MAX(0,A18-Параметры!$C$11-1))*Параметры!$C$15/12 -> 226302.08 | L18: =E18-I18-J18-K18 -> 1532881.2 | M18: =T17*Параметры!$C$10/12 -> 1115925.9 | N18: =L18-M18 -> 416955.35 | O18: =MAX(0,N18*Параметры!$C$14) -> 83391.071 | P18: =N18-O18 -> 333564.28 | Q18: 0 | R18: 0 | S18: =MAX(0,MIN(Параметры!$C$26-M18,T17)) -> 126336.06 | T18: =MAX(0,T17-S18) -> 89147736 | U18: =P18+J18-S18-H18 -> -7555.1077 | V18: =V17+U18 -> -41241989
A19: 18 | B19: 2028-01 | C19: Эксплуатация | D19: =Параметры!$C$4*Параметры!$C$7*(1+Параметры!$C$8)^INT((A19-Параметры!$C$11-1)/12) -> 2851200 | E19: =D19/(1+Параметры!$C$13) -> 2376000 | F19: =D19-E19 -> 475200 | G19: =IF(AND(A19>Параметры!$C$11,A19<=Параметры!$C$11+3),Параметры!$C$28,0) -> 0 | H19: =F19-G19 -> 475200 | I19: =E19*Параметры!$C$16 -> 356400 | J19: =Параметры!$C$27 -> 260416.67 | K19: =MAX(0,Параметры!$C$20-Параметры!$C$27*MAX(0,A19-Параметры!$C$11-1))*Параметры!$C$15/12 -> 225824.65 | L19: =E19-I19-J19-K19 -> 1533358.7 | M19: =T18*Параметры!$C$10/12 -> 1114346.7 | N19: =L19-M19 -> 419011.98 | O19: =MAX(0,N19*Параметры!$C$14) -> 83802.397 | P19: =N19-O19 -> 335209.59 | Q19: 0 | R19: 0 | S19: =MAX(0,MIN(Параметры!$C$26-M19,T18)) -> 127915.26 | T19: =MAX(0,T18-S19) -> 89019820 | U19: =P19+J19-S19-H19 -> -7489.0034 | V19: =V18+U19 -> -41249478
A20: 19 | B20: 2028-02 | C20: Эксплуатация | D20: =Параметры!$C$4*Параметры!$C$7*(1+Параметры!$C$8)^INT((A20-Параметры!$C$11-1)/12) -> 2851200 | E20: =D20/(1+Параметры!$C$13) -> 2376000 | F20: =D20-E20 -> 475200 | G20: =IF(AND(A20>Параметры!$C$11,A20<=Параметры!$C$11+3),Параметры!$C$28,0) -> 0 | H20: =F20-G20 -> 475200 | I20: =E20*Параметры!$C$16 -> 356400 | J20: =Параметры!$C$27 -> 260416.67 | K20: =MAX(0,Параметры!$C$20-Параметры!$C$27*MAX(0,A20-Параметры!$C$11-1))*Параметры!$C$15/12 -> 225347.22 | L20: =E20-I20-J20-K20 -> 1533836.1 | M20: =T19*Параметры!$C$10/12 -> 1112747.8 | N20: =L20-M20 -> 421088.36 | O20: =MAX(0,N20*Параметры!$C$14) -> 84217.671 | P20: =N20-O20 -> 336870.68 | Q20: 0 | R20: 0 | S20: =MAX(0,MIN(Параметры!$C$26-M20,T19)) -> 129514.2 | T20: =MAX(0,T19-S20) -> 88890306 | U20: =P20+J20-S20-H20 -> -7426.8471 | V20: =V19+U20 -> -41256905
A21: 20 | B21: 2028-03 | C21: Эксплуатация | D21: =Параметры!$C$4*Параметры!$C$7*(1+Параметры!$C$8)^INT((A21-Параметры!$C$11-1)/12) -> 2851200 | E21: =D21/(1+Параметры!$C$13) -> 2376000 | F21: =D21-E21 -> 475200 | G21: =IF(AND(A21>Параметры!$C$11,A21<=Параметры!$C$11+3),Параметры!$C$28,0) -> 0 | H21: =F21-G21 -> 475200 | I21: =E21*Параметры!$C$16 -> 356400 | J21: =Параметры!$C$27 -> 260416.67 | K21: =MAX(0,Параметры!$C$20-Параметры!$C$27*MAX(0,A21-Параметры!$C$11-1))*Параметры!$C$15/12 -> 224869.79 | L21: =E21-I21-J21-K21 -> 1534313.5 | M21: =T20*Параметры!$C$10/12 -> 1111128.8 | N21: =L21-M21 -> 423184.71 | O21: =MAX(0,N21*Параметры!$C$14) -> 84636.943 | P21: =N21-O21 -> 338547.77 | Q21: 0 | R21: 0 | S21: =MAX(0,MIN(Параметры!$C$26-M21,T20)) -> 131133.13 | T21: =MAX(0,T20-S21) -> 88759173 | U21: =P21+J21-S21-H21 -> -7368.6882 | V21: =V20+U21 -> -41264274
A22: 21 | B22: 2028-04 | C22: Эксплуатация | D22: =Параметры!$C$4*Параметры!$C$7*(1+Параметры!$C$8)^INT((A22-Параметры!$C$11-1)/12) -> 2851200 | E22: =D22/(1+Параметры!$C$13) -> 2376000 | F22: =D22-E22 -> 475200 | G22: =IF(AND(A22>Параметры!$C$11,A22<=Параметры!$C$11+3),Параметры!$C$28,0) -> 0 | H22: =F22-G22 -> 475200 | I22: =E22*Параметры!$C$16 -> 356400 | J22: =Параметры!$C$27 -> 260416.67 | K22: =MAX(0,Параметры!$C$20-Параметры!$C$27*MAX(0,A22-Параметры!$C$11-1))*Параметры!$C$15/12 -> 224392.36 | L22: =E22-I22-J22-K22 -> 1534791 | M22: =T21*Параметры!$C$10/12 -> 1109489.7 | N22: =L22-M22 -> 425301.31 | O22: =MAX(0,N22*Параметры!$C$14) -> 85060.262 | P22: =N22-O22 -> 340241.05 | Q22: 0 | R22: 0 | S22: =MAX(0,MIN(Параметры!$C$26-M22,T21)) -> 132772.29 | T22: =MAX(0,T21-S22) -> 88626401 | U22: =P22+J22-S22-H22 -> -7314.5765 | V22: =V21+U22 -> -41271588
A23: 22 | B23: 2028-05 | C23: Эксплуатация | D23: =Параметры!$C$4*Параметры!$C$7*(1+Параметры!$C$8)^INT((A23-Параметры!$C$11-1)/12) -> 2851200 | E23: =D23/(1+Параметры!$C$13) -> 2376000 | F23: =D23-E23 -> 475200 | G23: =IF(AND(A23>Параметры!$C$11,A23<=Параметры!$C$11+3),Параметры!$C$28,0) -> 0 | H23: =F23-G23 -> 475200 | I23: =E23*Параметры!$C$16 -> 356400 | J23: =Параметры!$C$27 -> 260416.67 | K23: =MAX(0,Параметры!$C$20-Параметры!$C$27*MAX(0,A23-Параметры!$C$11-1))*Параметры!$C$15/12 -> 223914.93 | L23: =E23-I23-J23-K23 -> 1535268.4 | M23: =T22*Параметры!$C$10/12 -> 1107830 | N23: =L23-M23 -> 427438.39 | O23: =MAX(0,N23*Параметры!$C$14) -> 85487.678 | P23: =N23-O23 -> 341950.71 | Q23: 0 | R23: 0 | S23: =MAX(0,MIN(Параметры!$C$26-M23,T22)) -> 134431.94 | T23: =MAX(0,T22-S23) -> 88491969 | U23: =P23+J23-S23-H23 -> -7264.5628 | V23: =V22+U23 -> -41278853
... A201: 200 | B201: 2043-03 | C201: Эксплуатация | D201: =Параметры!$C$4*Параметры!$C$7*(1+Параметры!$C$8)^INT((A201-Параметры!$C$11-1)/12) -> 9044488.6 | E201: =D201/(1+Параметры!$C$13) -> 7537073.8 | F201: =D201-E201 -> 1507414.8 | G201: =IF(AND(A201>Параметры!$C$11,A201<=Параметры!$C$11+3),Параметры!$C$28,0) -> 0 | H201: =F201-G201 -> 1507414.8 | I201: =E201*Параметры!$C$16 -> 1130561.1 | J201: =Параметры!$C$27 -> 260416.67 | K201: =MAX(0,Параметры!$C$20-Параметры!$C$27*MAX(0,A201-Параметры!$C$11-1))*Параметры!$C$15/12 -> 138932.29 | L201: =E201-I201-J201-K201 -> 6007163.8 | M201: =T200*Параметры!$C$10/12 -> 15336.567 | N201: =L201-M201 -> 5991827.2 | O201: =MAX(0,N201*Параметры!$C$14) -> 1198365.4 | P201: =N201-O201 -> 4793461.8 | Q201: 0 | R201: 0 | S201: =MAX(0,MIN(Параметры!$C$26-M201,T200)) -> 1226925.4 | T201: =MAX(0,T200-S201) -> 0 | U201: =P201+J201-S201-H201 -> 2319538.3 | V201: =V200+U201 -> 1.4168426e+08
A202: ИТОГО ЗА ГОРИЗОНТ | C202: =SUM(C2:C201) -> 0 | D202: =SUM(D2:D201) -> 1.0194382e+09 | E202: =SUM(E2:E201) -> 8.4953181e+08 | F202: =SUM(F2:F201) -> 1.6990636e+08 | G202: =SUM(G2:G201) -> 25000000 | H202: =SUM(H2:H201) -> 1.4490636e+08 | I202: =SUM(I2:I201) -> 1.2742977e+08 | J202: =SUM(J2:J201) -> 49479167 | ... V202: =SUM(V2:V201) -> 1.9924813e+09

Sheet ИТОГ
A1: КЛЮЧЕВЫЕ ПОКАЗАТЕЛИ ПРОЕКТА
A2: Проект | C2: =Параметры!$C$2 -> Sklad_160
A3: Дата начала | C3: =Параметры!$C$3 -> 2026-07
A4: Горизонт планирования | C4: =Параметры!$C$12&" мес." -> 200 мес.
A5: ПОКАЗАТЕЛИ ЭФФЕКТИВНОСТИ
A6: NPV (чистая приведённая стоимость) | B6: руб. | C6: =NPV(Параметры!$C$9/12,'Денежные потоки'!U2:U201) -> -1794052.9
A7: IRR (годовая внутренняя норма доходности) | B7: % | C7: =IFERROR((1+IRR('Денежные потоки'!U2:U201))^12-1,"Н/Д") -> 0.14416084
A8: ROI (рентабельность СС за горизонт) | B8: % | C8: =IFERROR(SUM('Денежные потоки'!P2:P201)/Параметры!$C$23,"Н/Д") -> 6.5549827
A9: Срок окупаемости | B9: мес. | C9: {=MATCH(TRUE,'Денежные потоки'!V2:V201>=0,0)} -> 113
A10: Ставка дисконтирования (ЦБ) | B10: % | C10: =Параметры!$C$9 -> 0.14
A11: ФИНАНСОВЫЕ ИТОГИ ЗА ГОРИЗОНТ
A12: Суммарная выручка (с НДС) | B12: руб. | C12: =SUM('Денежные потоки'!D2:D201) -> 1.0194382e+09
A13: Суммарная выручка (без НДС) | B13: руб. | C13: =SUM('Денежные потоки'!E2:E201) -> 8.4953181e+08
A14: Операционные расходы | B14: руб. | C14: =SUM('Денежные потоки'!I2:I201) -> 1.2742977e+08
A15: Чистая прибыль (суммарно) | B15: руб. | C15: =SUM('Денежные потоки'!P2:P201) -> 3.9329896e+08
A16: НАЛОГИ И ПЛАТЕЖИ ЗА ГОРИЗОНТ
A17: Налог на прибыль | B17: руб. | C17: =SUM('Денежные потоки'!O2:O201) -> 98324740
A18: НДС к уплате (выплаты в бюджет) | B18: руб. | C18: =SUMIF('Денежные потоки'!H2:H201,">0",'Денежные потоки'!H2:H201) -> 1.6848076e+08
A19: Возврат НДС из строительства | B19: руб. | C19: =SUM('Денежные потоки'!G2:G201) -> 25000000
A20: Налог на имущество | B20: руб. | C20: =SUM('Денежные потоки'!K2:K201) -> 34969401
A21: Проценты по кредиту | B21: руб. | C21: =SUM('Денежные потоки'!M2:M201) -> 1.5221727e+08
A22: СТРУКТУРА ФИНАНСИРОВАНИЯ
A23: Собственные средства | B23: руб. | C23: =Параметры!$C$23 -> 60000000
A24: Кредит | B24: руб. | C24: =Параметры!$C$22 -> 90000000
A25: Итого инвестиций | B25: руб. | C25: =Параметры!$C$5 -> 150000000

Sheet Чувствительность
A1: АНАЛИЗ ЧУВСТВИТЕЛЬНОСТИ
A2: Параметр | B2: Сценарий (пессимист) | C2: Базовый | D2: Сценарий (оптимист) | E2: NPV пессимист | F2: NPV базовый | G2: NPV оптимист
A3: Таблица заполняется командой /sensitivity <name>. Для пересчёта сценариев вручную измените параметры на листе «Параметры».
