Workbook

Sheet Параметры
A1: ВХОДНЫЕ ПАРАМЕТРЫ ПРОЕКТА
A2: Название проекта | C2: Sklad_Zlatoust
A3: Дата начала строительства | B3: ДД.ММ.ГГГГ | C3: 01.06.2026
A4: Площадь объекта | B4: кв.м. | C4: 2000
A5: Себестоимость строительства (с НДС) | B5: руб. | C5: 100000000
A6: Доля кредита | C6: 0.65
A7: Арендная ставка | B7: руб./кв.м./мес. | C7: 1464
A8: Годовая инфляция (индексация аренды) | C8: 0.08
A9: Ставка ЦБ (ставка дисконтирования) | C9: 0.145
A10: Кредитная ставка | C10: 0.2
A11: Срок строительства | B11: мес. | C11: 12
A12: Горизонт планирования | B12: мес. | C12: 180
A13: Ставка НДС | C13: 0.22
A14: Ставка налога на прибыль | C14: 0.2
A15: Ставка налога на имущество | B15: в год | C15: 0.022
A16: Операционные расходы | B16: % от выручки б/НДС | C16: 0.15
A17: Срок полезного использования | B17: лет | C17: 40
A18: РАСЧЁТНЫЕ (ПРОИЗВОДНЫЕ) ПАРАМЕТРЫ
A19: Изменяйте только синие ячейки выше — формулы ниже пересчитаются автоматически.
A20: Себестоимость без НДС | B20: руб. | C20: =C5/(1+C13) -> 81967213
A21: НДС строительства | B21: руб. | C21: =C5-C20 -> 18032787
A22: Сумма кредита | B22: руб. | C22: =C5*C6 -> 65000000
A23: Собственные средства | B23: руб. | C23: =C5*(1-C6) -> 35000000
A24: Стоимость 1 кв.м. | B24: руб. | C24: =C5/C4 -> 50000
A25: Период эксплуатации | B25: мес. | C25: =C12-C11 -> 168
A26: Аннуитетный платёж (в мес.) | B26: руб./мес. | C26: =-PMT(C10/12,C12-C11,C5*C6) -> 1155222.5
A27: Амортизация (в мес.) | B27: руб./мес. | C27: =C20/(C17*12) -> 170765.03
A28: НДС к возмещению (1-3 мес. экспл.) | B28: руб./мес. | C28: =(C5-C5/(1+C13))/3 -> 6010929

Sheet Денежные потоки
A1: Мес. | B1: Дата | C1: Фаза | D1: Выручка с НДС | E1: Выручка без НДС | F1: НДС выходной | G1: НДС входной | H1: НДС нетто | I1: Опер. расходы | J1: Амортизация | K1: Налог на имущ. | L1: EBIT | M1: Проценты | N1: EBT | O1: Налог на прибыль | P1: Чистая прибыль | Q1: Капвложения | R1: Транш кредита | S1: Погашение кредита | T1: Остаток кредита | U1: CF инвестора | V1: Накопл. CF
A2: 1 | B2: 01.07.2026 | C2: Строительство | D2: 0 | E2: 0 | F2: 0 | G2: 0 | H2: 0 | I2: 0 | J2: 0 | K2: 0 | L2: 0 | M2: =T2*Параметры!$C$10/12 -> 90277.778 | N2: =-M2 -> -90277.778 | O2: 0 | P2: 0 | Q2: =Параметры!$C$5/Параметры!$C$11 -> 8333333.3 | R2: =Параметры!$C$22/Параметры!$C$11 -> 5416666.7 | S2: 0 | T2: =Параметры!$C$22/Параметры!$C$11*A2 -> 5416666.7 | U2: =-(Параметры!$C$23/Параметры!$C$11+M2) -> -3006944.4 | V2: =U2 -> -3006944.4
A3: 2 | B3: 01.08.2026 | C3: Строительство | D3: 0 | E3: 0 | F3: 0 | G3: 0 | H3: 0 | I3: 0 | J3: 0 | K3: 0 | L3: 0 | M3: =T3*Параметры!$C$10/12 -> 180555.56 | N3: =-M3 -> -180555.56 | O3: 0 | P3: 0 | Q3: =Параметры!$C$5/Параметры!$C$11 -> 8333333.3 | R3: =Параметры!$C$22/Параметры!$C$11 -> 5416666.7 | S3: 0 | T3: =Параметры!$C$22/Параметры!$C$11*A3 -> 10833333 | U3: =-(Параметры!$C$23/Параметры!$C$11+M3) -> -3097222.2 | V3: =V2+U3 -> -6104166.7
A4: 3 | B4: 01.09.2026 | C4: Строительство | D4: 0 | E4: 0 | F4: 0 | G4: 0 | H4: 0 | I4: 0 | J4: 0 | K4: 0 | L4: 0 | M4: =T4*Параметры!$C$10/12 -> 270833.33 | N4: =-M4 -> -270833.33 | O4: 0 | P4: 0 | Q4: =Параметры!$C$5/Параметры!$C$11 -> 8333333.3 | R4: =Параметры!$C$22/Параметры!$C$11 -> 5416666.7 | S4: 0 | T4: =Параметры!$C$22/Параметры!$C$11*A4 -> 16250000 | U4: =-(Параметры!$C$23/Параметры!$C$11+M4) -> -3187500 | V4: =V3+U4 -> -9291666.7
A5: 4 | B5: 01.10.2026 | C5: Строительство | D5: 0 | E5: 0 | F5: 0 | G5: 0 | H5: 0 | I5: 0 | J5: 0 | K5: 0 | L5: 0 | M5: =T5*Параметры!$C$10/12 -> 361111.11 | N5: =-M5 -> -361111.11 | O5: 0 | P5: 0 | Q5: =Параметры!$C$5/Параметры!$C$11 -> 8333333.3 | R5: =Параметры!$C$22/Параметры!$C$11 -> 5416666.7 | S5: 0 | T5: =Параметры!$C$22/Параметры!$C$11*A5 -> 21666667 | U5: =-(Параметры!$C$23/Параметры!$C$11+M5) -> -3277777.8 | V5: =V4+U5 -> -12569444
A6: 5 | B6: 01.11.2026 | C6: Строительство | D6: 0 | E6: 0 | F6: 0 | G6: 0 | H6: 0 | I6: 0 | J6: 0 | K6: 0 | L6: 0 | M6: =T6*Параметры!$C$10/12 -> 451388.89 | N6: =-M6 -> -451388.89 | O6: 0 | P6: 0 | Q6: =Параметры!$C$5/Параметры!$C$11 -> 8333333.3 | R6: =Параметры!$C$22/Параметры!$C$11 -> 5416666.7 | S6: 0 | T6: =Параметры!$C$22/Параметры!$C$11*A6 -> 27083333 | U6: =-(Параметры!$C$23/Параметры!$C$11+M6) -> -3368055.6 | V6: =V5+U6 -> -15937500
A7: 6 | B7: 01.12.2026 | C7: Строительство | D7: 0 | E7: 0 | F7: 0 | G7: 0 | H7: 0 | I7: 0 | J7: 0 | K7: 0 | L7: 0 | M7: =T7*Параметры!$C$10/12 -> 541666.67 | N7: =-M7 -> -541666.67 | O7: 0 | P7: 0 | Q7: =Параметры!$C$5/Параметры!$C$11 -> 8333333.3 | R7: =Параметры!$C$22/Параметры!$C$11 -> 5416666.7 | S7: 0 | T7: =Параметры!$C$22/Параметры!$C$11*A7 -> 32500000 | U7: =-(Параметры!$C$23/Параметры!$C$11+M7) -> -3458333.3 | V7: =V6+U7 -> -19395833
A8: 7 | B8: 01.01.2027 | C8: Строительство | D8: 0 | E8: 0 | F8: 0 | G8: 0 | H8: 0 | I8: 0 | J8: 0 | K8: 0 | L8: 0 | M8: =T8*Параметры!$C$10/12 -> 631944.44 | N8: =-M8 -> -631944.44 | O8: 0 | P8: 0 | Q8: =Параметры!$C$5/Параметры!$C$11 -> 8333333.3 | R8: =Параметры!$C$22/Параметры!$C$11 -> 5416666.7 | S8: 0 | T8: =Параметры!$C$22/Параметры!$C$11*A8 -> 37916667 | U8: =-(Параметры!$C$23/Параметры!$C$11+M8) -> -3548611.1 | V8: =V7+U8 -> -22944444
A9: 8 | B9: 01.02.2027 | C9: Строительство | D9: 0 | E9: 0 | F9: 0 | G9: 0 | H9: 0 | I9: 0 | J9: 0 | K9: 0 | L9: 0 | M9: =T9*Параметры!$C$10/12 -> 722222.22 | N9: =-M9 -> -722222.22 | O9: 0 | P9: 0 | Q9: =Параметры!$C$5/Параметры!$C$11 -> 8333333.3 | R9: =Параметры!$C$22/Параметры!$C$11 -> 5416666.7 | S9: 0 | T9: =Параметры!$C$22/Параметры!$C$11*A9 -> 43333333 | U9: =-(Параметры!$C$23/Параметры!$C$11+M9) -> -3638888.9 | V9: =V8+U9 -> -26583333
A10: 9 | B10: 01.03.2027 | C10: Строительство | D10: 0 | E10: 0 | F10: 0 | G10: 0 | H10: 0 | I10: 0 | J10: 0 | K10: 0 | L10: 0 | M10: =T10*Параметры!$C$10/12 -> 812500 | N10: =-M10 -> -812500 | O10: 0 | P10: 0 | Q10: =Параметры!$C$5/Параметры!$C$11 -> 8333333.3 | R10: =Параметры!$C$22/Параметры!$C$11 -> 5416666.7 | S10: 0 | T10: =Параметры!$C$22/Параметры!$C$11*A10 -> 48750000 | U10: =-(Параметры!$C$23/Параметры!$C$11+M10) -> -3729166.7 | V10: =V9+U10 -> -30312500
A11: 10 | B11: 01.04.2027 | C11: Строительство | D11: 0 | E11: 0 | F11: 0 | G11: 0 | H11: 0 | I11: 0 | J11: 0 | K11: 0 | L11: 0 | M11: =T11*Параметры!$C$10/12 -> 902777.78 | N11: =-M11 -> -902777.78 | O11: 0 | P11: 0 | Q11: =Параметры!$C$5/Параметры!$C$11 -> 8333333.3 | R11: =Параметры!$C$22/Параметры!$C$11 -> 5416666.7 | S11: 0 | T11: =Параметры!$C$22/Параметры!$C$11*A11 -> 54166667 | U11: =-(Параметры!$C$23/Параметры!$C$11+M11) -> -3819444.4 | V11: =V10+U11 -> -34131944
A12: 11 | B12: 01.05.2027 | C12: Строительство | D12: 0 | E12: 0 | F12: 0 | G12: 0 | H12: 0 | I12: 0 | J12: 0 | K12: 0 | L12: 0 | M12: =T12*Параметры!$C$10/12 -> 993055.56 | N12: =-M12 -> -993055.56 | O12: 0 | P12: 0 | Q12: =Параметры!$C$5/Параметры!$C$11 -> 8333333.3 | R12: =Параметры!$C$22/Параметры!$C$11 -> 5416666.7 | S12: 0 | T12: =Параметры!$C$22/Параметры!$C$11*A12 -> 59583333 | U12: =-(Параметры!$C$23/Параметры!$C$11+M12) -> -3909722.2 | V12: =V11+U12 -> -38041667
A13: 12 | B13: 01.06.2027 | C13: Строительство | D13: 0 | E13: 0 | F13: 0 | G13: 0 | H13: 0 | I13: 0 | J13: 0 | K13: 0 | L13: 0 | M13: =T13*Параметры!$C$10/12 -> 1083333.3 | N13: =-M13 -> -1083333.3 | O13: 0 | P13: 0 | Q13: =Параметры!$C$5/Параметры!$C$11 -> 8333333.3 | R13: =Параметры!$C$22/Параметры!$C$11 -> 5416666.7 | S13: 0 | T13: =Параметры!$C$22/Параметры!$C$11*A13 -> 65000000 | U13: =-(Параметры!$C$23/Параметры!$C$11+M13) -> -4000000 | V13: =V12+U13 -> -42041667
A14: 13 | B14: 01.07.2027 | C14: Эксплуатация | D14: =Параметры!$C$4*Параметры!$C$7*(1+Параметры!$C$8)^INT((A14-Параметры!$C$11-1)/12) -> 2928000 | E14: =D14/(1+Параметры!$C$13) -> 2400000 | F14: =D14-E14 -> 528000 | G14: =IF(AND(A14>Параметры!$C$11,A14<=Параметры!$C$11+3),Параметры!$C$28,0) -> 6010929 | H14: =F14-G14 -> -5482929 | I14: =E14*Параметры!$C$16 -> 360000 | J14: =Параметры!$C$27 -> 170765.03 | K14: =MAX(0,Параметры!$C$20-Параметры!$C$27*MAX(0,A14-Параметры!$C$11-1))*Параметры!$C$15/12 -> 150273.22 | L14: =E14-I14-J14-K14 -> 1718961.7 | M14: =T13*Параметры!$C$10/12 -> 1083333.3 | N14: =L14-M14 -> 635628.42 | O14: =MAX(0,N14*Параметры!$C$14) -> 127125.68 | P14: =N14-O14 -> 508502.73 | Q14: 0 | R14: 0 | S14: =MAX(0,MIN(Параметры!$C$26-M14,T13)) -> 71889.162 | T14: =MAX(0,T13-S14) -> 64928111 | U14: =P14+J14-S14-H14 -> 6090307.6 | V14: =V13+U14 -> -35951359
A15: 14 | B15: 01.08.2027 | C15: Эксплуатация | D15: =Параметры!$C$4*Параметры!$C$7*(1+Параметры!$C$8)^INT((A15-Параметры!$C$11-1)/12) -> 2928000 | E15: =D15/(1+Параметры!$C$13) -> 2400000 | F15: =D15-E15 -> 528000 | G15: =IF(AND(A15>Параметры!$C$11,A15<=Параметры!$C$11+3),Параметры!$C$28,0) -> 6010929 | H15: =F15-G15 -> -5482929 | I15: =E15*Параметры!$C$16 -> 360000 | J15: =Параметры!$C$27 -> 170765.03 | K15: =MAX(0,Параметры!$C$20-Параметры!$C$27*MAX(0,A15-Параметры!$C$11-1))*Параметры!$C$15/12 -> 149960.15 | L15: =E15-I15-J15-K15 -> 1719274.8 | M15: =T14*Параметры!$C$10/12 -> 1082135.2 | N15: =L15-M15 -> 637139.64 | O15: =MAX(0,N15*Параметры!$C$14) -> 127427.93 | P15: =N15-O15 -> 509711.71 | Q15: 0 | R15: 0 | S15: =MAX(0,MIN(Параметры!$C$26-M15,T14)) -> 73087.314 | T15: =MAX(0,T14-S15) -> 64855024 | U15: =P15+J15-S15-H15 -> 6090318.4 | V15: =V14+U15 -> -29861041
A16: 15 | B16: 01.09.2027 | C16: Эксплуатация | D16: =Параметры!$C$4*Параметры!$C$7*(1+Параметры!$C$8)^INT((A16-Параметры!$C$11-1)/12) -> 2928000 | E16: =D16/(1+Параметры!$C$13) -> 2400000 | F16: =D16-E16 -> 528000 | G16: =IF(AND(A16>Параметры!$C$11,A16<=Параметры!$C$11+3),Параметры!$C$28,0) -> 6010929 | H16: =F16-G16 -> -5482929 | I16: =E16*Параметры!$C$16 -> 360000 | J16: =Параметры!$C$27 -> 170765.03 | K16: =MAX(0,Параметры!$C$20-Параметры!$C$27*MAX(0,A16-Параметры!$C$11-1))*Параметры!$C$15/12 -> 149647.09 | L16: =E16-I16-J16-K16 -> 1719587.9 | M16: =T15*Параметры!$C$10/12 -> 1080917.1 | N16: =L16-M16 -> 638670.83 | O16: =MAX(0,N16*Параметры!$C$14) -> 127734.17 | P16: =N16-O16 -> 510936.66 | Q16: 0 | R16: 0 | S16: =MAX(0,MIN(Параметры!$C$26-M16,T15)) -> 74305.436 | T16: =MAX(0,T15-S16) -> 64780718 | U16: =P16+J16-S16-H16 -> 6090325.2 | V16: =V15+U16 -> -23770716
A17: 16 | B17: 01.10.2027 | C17: Эксплуатация | D17: =Параметры!$C$4*Параметры!$C$7*(1+Параметры!$C$8)^INT((A17-Параметры!$C$11-1)/12) -> 2928000 | E17: =D17/(1+Параметры!$C$13) -> 2400000 | F17: =D17-E17 -> 528000 | G17: =IF(AND(A17>Параметры!$C$11,A17<=Параметры!$C$11+3),Параметры!$C$28,0) -> 0 | H17: =F17-G17 -> 528000 | I17: =E17*Параметры!$C$16 -> 360000 | J17: =Параметры!$C$27 -> 170765.03 | K17: =MAX(0,Параметры!$C$20-Параметры!$C$27*MAX(0,A17-Параметры!$C$11-1))*Параметры!$C$15/12 -> 149334.02 | L17: =E17-I17-J17-K17 -> 1719901 | M17: =T16*Параметры!$C$10/12 -> 1079678.6 | N17: =L17-M17 -> 640222.32 | O17: =MAX(0,N17*Параметры!$C$14) -> 128044.46 | P17: =N17-O17 -> 512177.86 | Q17: 0 | R17: 0 | S17: =MAX(0,MIN(Параметры!$C$26-M17,T16)) -> 75543.86 | T17: =MAX(0,T16-S17) -> 64705174 | U17: =P17+J17-S17-H17 -> 79399.024 | V17: =V16+U17 -> -23691316
A18: 17 | B18: 01.11.2027 | C18: Эксплуатация | D18: =Параметры!$C$4*Параметры!$C$7*(1+Параметры!$C$8)^INT((A18-Параметры!$C$11-1)/12) -> 2928000 | E18: =D18/(1+Параметры!$C$13) -> 2400000 | F18: =D18-E18 -> 528000 | G18: =IF(AND(A18>Параметры!$C$11,A18<=Параметры!$C$11+3),Параметры!$C$28,0) -> 0 | H18: =F18-G18 -> 528000 | I18: =E18*Параметры!$C$16 -> 360000 | J18: =Параметры!$C$27 -> 170765.03 | K18: =MAX(0,Параметры!$C$20-Параметры!$C$27*MAX(0,A18-Параметры!$C$11-1))*Параметры!$C$15/12 -> 149020.95 | L18: =E18-I18-J18-K18 -> 1720214 | M18: =T17*Параметры!$C$10/12 -> 1078419.6 | N18: =L18-M18 -> 641794.46 | O18: =MAX(0,N18*Параметры!$C$14) -> 128358.89 | P18: =N18-O18 -> 513435.56 | Q18: 0 | R18: 0 | S18: =MAX(0,MIN(Параметры!$C$26-M18,T17)) -> 76802.925 | T18: =MAX(0,T17-S18) -> 64628371 | U18: =P18+J18-S18-H18 -> 79397.667 | V18: =V17+U18 -> -23611919
A19: 18 | B19: 01.12.2027 | C19: Эксплуатация | D19: =Параметры!$C$4*Параметры!$C$7*(1+Параметры!$C$8)^INT((A19-Параметры!$C$11-1)/12) -> 2928000 | E19: =D19/(1+Параметры!$C$13) -> 2400000 | F19: =D19-E19 -> 528000 | G19: =IF(AND(A19>Параметры!$C$11,A19<=Параметры!$C$11+3),Параметры!$C$28,0) -> 0 | H19: =F19-G19 -> 528000 | I19: =E19*Параметры!$C$16 -> 360000 | J19: =Параметры!$C$27 -> 170765.03 | K19: =MAX(0,Параметры!$C$20-Параметры!$C$27*MAX(0,A19-Параметры!$C$11-1))*Параметры!$C$15/12 -> 148707.88 | L19: =E19-I19-J19-K19 -> 1720527.1 | M19: =T18*Параметры!$C$10/12 -> 1077139.5 | N19: =L19-M19 -> 643387.57 | O19: =MAX(0,N19*Параметры!$C$14) -> 128677.51 | P19: =N19-O19 -> 514710.06 | Q19: 0 | R19: 0 | S19: =MAX(0,MIN(Параметры!$C$26-M19,T18)) -> 78082.973 | T19: =MAX(0,T18-S19) -> 64550288 | U19: =P19+J19-S19-H19 -> 79392.112 | V19: =V18+U19 -> -23532527
A20: 19 | B20: 01.01.2028 | C20: Эксплуатация | D20: =Параметры!$C$4*Параметры!$C$7*(1+Параметры!$C$8)^INT((A20-Параметры!$C$11-1)/12) -> 2928000 | E20: =D20/(1+Параметры!$C$13) -> 2400000 | F20: =D20-E20 -> 528000 | G20: =IF(AND(A20>Параметры!$C$11,A20<=Параметры!$C$11+3),Параметры!$C$28,0) -> 0 | H20: =F20-G20 -> 528000 | I20: =E20*Параметры!$C$16 -> 360000 | J20: =Параметры!$C$27 -> 170765.03 | K20: =MAX(0,Параметры!$C$20-Параметры!$C$27*MAX(0,A20-Параметры!$C$11-1))*Параметры!$C$15/12 -> 148394.81 | L20: =E20-I20-J20-K20 -> 1720840.2 | M20: =T19*Параметры!$C$10/12 -> 1075838.1 | N20: =L20-M20 -> 645002.03 | O20: =MAX(0,N20*Параметры!$C$14) -> 129000.41 | P20: =N20-O20 -> 516001.62 | Q20: 0 | R20: 0 | S20: =MAX(0,MIN(Параметры!$C$26-M20,T19)) -> 79384.356 | T20: =MAX(0,T19-S20) -> 64470904 | U20: =P20+J20-S20-H20 -> 79382.291 | V20: =V19+U20 -> -23453144
A21: 20 | B21: 01.02.2028 | C21: Эксплуатация | D21: =Параметры!$C$4*Параметры!$C$7*(1+Параметры!$C$8)^INT((A21-Параметры!$C$11-1)/12) -> 2928000 | E21: =D21/(1+Параметры!$C$13) -> 2400000 | F21: =D21-E21 -> 528000 | G21: =IF(AND(A21>Параметры!$C$11,A21<=Параметры!$C$11+3),Параметры!$C$28,0) -> 0 | H21: =F21-G21 -> 528000 | I21: =E21*Параметры!$C$16 -> 360000 | J21: =Параметры!$C$27 -> 170765.03 | K21: =MAX(0,Параметры!$C$20-Параметры!$C$27*MAX(0,A21-Параметры!$C$11-1))*Параметры!$C$15/12 -> 148081.74 | L21: =E21-I21-J21-K21 -> 1721153.2 | M21: =T20*Параметры!$C$10/12 -> 1074515.1 | N21: =L21-M21 -> 646638.17 | O21: =MAX(0,N21*Параметры!$C$14) -> 129327.63 | P21: =N21-O21 -> 517310.53 | Q21: 0 | R21: 0 | S21: =MAX(0,MIN(Параметры!$C$26-M21,T20)) -> 80707.429 | T21: =MAX(0,T20-S21) -> 64390197 | U21: =P21+J21-S21-H21 -> 79368.132 | V21: =V20+U21 -> -23373776
A22: 21 | B22: 01.03.2028 | C22: Эксплуатация | D22: =Параметры!$C$4*Параметры!$C$7*(1+Параметры!$C$8)^INT((A22-Параметры!$C$11-1)/12) -> 2928000 | E22: =D22/(1+Параметры!$C$13) -> 2400000 | F22: =D22-E22 -> 528000 | G22: =IF(AND(A22>Параметры!$C$11,A22<=Параметры!$C$11+3),Параметры!$C$28,0) -> 0 | H22: =F22-G22 -> 528000 | I22: =E22*Параметры!$C$16 -> 360000 | J22: =Параметры!$C$27 -> 170765.03 | K22: =MAX(0,Параметры!$C$20-Параметры!$C$27*MAX(0,A22-Параметры!$C$11-1))*Параметры!$C$15/12 -> 147768.67 | L22: =E22-I22-J22-K22 -> 1721466.3 | M22: =T21*Параметры!$C$10/12 -> 1073169.9 | N22: =L22-M22 -> 648296.36 | O22: =MAX(0,N22*Параметры!$C$14) -> 129659.27 | P22: =N22-O22 -> 518637.09 | Q22: 0 | R22: 0 | S22: =MAX(0,MIN(Параметры!$C$26-M22,T21)) -> 82052.553 | T22: =MAX(0,T21-S22) -> 64308144 | U22: =P22+J22-S22-H22 -> 79349.563 | V22: =V21+U22 -> -23294427
A23: 22 | B23: 01.04.2028 | C23: Эксплуатация | D23: =Параметры!$C$4*Параметры!$C$7*(1+Параметры!$C$8)^INT((A23-Параметры!$C$11-1)/12) -> 2928000 | E23: =D23/(1+Параметры!$C$13) -> 2400000 | F23: =D23-E23 -> 528000 | G23: =IF(AND(A23>Параметры!$C$11,A23<=Параметры!$C$11+3),Параметры!$C$28,0) -> 0 | H23: =F23-G23 -> 528000 | I23: =E23*Параметры!$C$16 -> 360000 | J23: =Параметры!$C$27 -> 170765.03 | K23: =MAX(0,Параметры!$C$20-Параметры!$C$27*MAX(0,A23-Параметры!$C$11-1))*Параметры!$C$15/12 -> 147455.6 | L23: =E23-I23-J23-K23 -> 1721779.4 | M23: =T22*Параметры!$C$10/12 -> 1071802.4 | N23: =L23-M23 -> 649976.97 | O23: =MAX(0,N23*Параметры!$C$14) -> 129995.39 | P23: =N23-O23 -> 519981.58 | Q23: 0 | R23: 0 | S23: =MAX(0,MIN(Параметры!$C$26-M23,T22)) -> 83420.095 | T23: =MAX(0,T22-S23) -> 64224724 | U23: =P23+J23-S23-H23 -> 79326.509 | V23: =V22+U23 -> -23215100
A24: 23 | B24: 01.05.2028 | C24: Эксплуатация | D24: =Параметры!$C$4*Параметры!$C$7*(1+Параметры!$C$8)^INT((A24-Параметры!$C$11-1)/12) -> 2928000 | E24: =D24/(1+Параметры!$C$13) -> 2400000 | F24: =D24-E24 -> 528000 | G24: =IF(AND(A24>Параметры!$C$11,A24<=Параметры!$C$11+3),Параметры!$C$28,0) -> 0 | H24: =F24-G24 -> 528000 | I24: =E24*Параметры!$C$16 -> 360000 | J24: =Параметры!$C$27 -> 170765.03 | K24: =MAX(0,Параметры!$C$20-Параметры!$C$27*MAX(0,A24-Параметры!$C$11-1))*Параметры!$C$15/12 -> 147142.53 | L24: =E24-I24-J24-K24 -> 1722092.4 | M24: =T23*Параметры!$C$10/12 -> 1070412.1 | N24: =L24-M24 -> 651680.38 | O24: =MAX(0,N24*Параметры!$C$14) -> 130336.08 | P24: =N24-O24 -> 521344.3 | Q24: 0 | R24: 0 | S24: =MAX(0,MIN(Параметры!$C$26-M24,T23)) -> 84810.43 | T24: =MAX(0,T23-S24) -> 64139913 | U24: =P24+J24-S24-H24 -> 79298.898 | V24: =V23+U24 -> -23135801
A25: 24 | B25: 01.06.2028 | C25: Эксплуатация | D25: =Параметры!$C$4*Параметры!$C$7*(1+Параметры!$C$8)^INT((A25-Параметры!$C$11-1)/12) -> 2928000 | E25: =D25/(1+Параметры!$C$13) -> 2400000 | F25: =D25-E25 -> 528000 | G25: =IF(AND(A25>Параметры!$C$11,A25<=Параметры!$C$11+3),Параметры!$C$28,0) -> 0 | H25: =F25-G25 -> 528000 | I25: =E25*Параметры!$C$16 -> 360000 | J25: =Параметры!$C$27 -> 170765.03 | K25: =MAX(0,Параметры!$C$20-Параметры!$C$27*MAX(0,A25-Параметры!$C$11-1))*Параметры!$C$15/12 -> 146829.46 | L25: =E25-I25-J25-K25 -> 1722405.5 | M25: =T24*Параметры!$C$10/12 -> 1068998.6 | N25: =L25-M25 -> 653406.95 | O25: =MAX(0,N25*Параметры!$C$14) -> 130681.39 | P25: =N25-O25 -> 522725.56 | Q25: 0 | R25: 0 | S25: =MAX(0,MIN(Параметры!$C$26-M25,T24)) -> 86223.937 | T25: =MAX(0,T24-S25) -> 64053690 | U25: =P25+J25-S25-H25 -> 79266.652 | V25: =V24+U25 -> -23056535
... A181: 180 | B181: 01.06.2041 | C181: Эксплуатация | D181: =Параметры!$C$4*Параметры!$C$7*(1+Параметры!$C$8)^INT((A181-Параметры!$C$11-1)/12) -> 7963058.3 | E181: =D181/(1+Параметры!$C$13) -> 6527096.9 | F181: =D181-E181 -> 1435961.3 | G181: =IF(AND(A181>Параметры!$C$11,A181<=Параметры!$C$11+3),Параметры!$C$28,0) -> 0 | H181: =F181-G181 -> 1435961.3 | I181: =E181*Параметры!$C$16 -> 979064.54 | J181: =Параметры!$C$27 -> 170765.03 | K181: =MAX(0,Параметры!$C$20-Параметры!$C$27*MAX(0,A181-Параметры!$C$11-1))*Параметры!$C$15/12 -> 97990.665 | L181: =E181-I181-J181-K181 -> 5279276.7 | M181: =T180*Параметры!$C$10/12 -> 18938.074 | N181: =L181-M181 -> 5260338.6 | O181: =MAX(0,N181*Параметры!$C$14) -> 1052067.7 | P181: =N181-O181 -> 4208270.9 | Q181: 0 | R181: 0 | S181: =MAX(0,MIN(Параметры!$C$26-M181,T180)) -> 1136284.4 | T181: =MAX(0,T180-S181) -> 5.3318217e-07 | U181: =P181+J181-S181-H181 -> 1806790.2 | V181: =V180+U181 -> 1.1758285e+08
A182: ИТОГО ЗА ГОРИЗОНТ | C182: =SUM(C2:C181) -> 0 | D182: =SUM(D2:D181) -> 8.5081544e+08 | E182: =SUM(E2:E181) -> 6.973897e+08 | F182: =SUM(F2:F181) -> 1.5342574e+08 | G182: =SUM(G2:G181) -> 18032787 | H182: =SUM(H2:H181) -> 1.3539295e+08 | I182: =SUM(I2:I181) -> 1.0460846e+08 | J182: =SUM(J2:J181) -> 28688525 | ... V182: =SUM(V2:V181) -> 3.2808308e+09

Sheet ИТОГ
A1: КЛЮЧЕВЫЕ ПОКАЗАТЕЛИ ПРОЕКТА
A2: Проект | C2: =Параметры!$C$2 -> Sklad_Zlatoust
A3: Дата начала | C3: =Параметры!$C$3 -> 01.06.2026
A4: Горизонт планирования | C4: =Параметры!$C$12&" мес." -> 180 мес.
A5: ПОКАЗАТЕЛИ ЭФФЕКТИВНОСТИ
A6: NPV (чистая приведённая стоимость) | B6: руб. | C6: =NPV(Параметры!$C$9/12,'Денежные потоки'!U2:U181) -> 11126182
A7: IRR (годовая внутренняя норма доходности) | B7: % | C7: =IFERROR((1+IRR('Денежные потоки'!U2:U181))^12-1,"Н/Д") -> 0.20966907
A8: ROI (рентабельность СС за горизонт) | B8: % | C8: =IFERROR(SUM('Денежные потоки'!P2:P181)/Параметры!$C$23,"Н/Д") -> 9.4665412
A9: Срок окупаемости | B9: мес. | C9: {=MATCH(TRUE,'Денежные потоки'!V2:V181>=0,0)} -> 86
A10: Ставка дисконтирования (ЦБ) | B10: % | C10: =Параметры!$C$9 -> 0.145
A11: ФИНАНСОВЫЕ ИТОГИ ЗА ГОРИЗОНТ
A12: Суммарная выручка (с НДС) | B12: руб. | C12: =SUM('Денежные потоки'!D2:D181) -> 8.5081544e+08
A13: Суммарная выручка (без НДС) | B13: руб. | C13: =SUM('Денежные потоки'!E2:E181) -> 6.973897e+08
A14: Операционные расходы | B14: руб. | C14: =SUM('Денежные потоки'!I2:I181) -> 1.0460846e+08
A15: Чистая прибыль (суммарно) | B15: руб. | C15: =SUM('Денежные потоки'!P2:P181) -> 3.3132894e+08
A16: НАЛОГИ И ПЛАТЕЖИ ЗА ГОРИЗОНТ
A17: Налог на прибыль | B17: руб. | C17: =SUM('Денежные потоки'!O2:O181) -> 82832236
A18: НДС к уплате (выплаты в бюджет) | B18: руб. | C18: =SUMIF('Денежные потоки'!H2:H181,">0",'Денежные потоки'!H2:H181) -> 1.5184174e+08
A19: Возврат НДС из строительства | B19: руб. | C19: =SUM('Денежные потоки'!G2:G181) -> 18032787
A20: Налог на имущество | B20: руб. | C20: =SUM('Денежные потоки'!K2:K181) -> 20854167
A21: Проценты по кредиту | B21: руб. | C21: =SUM('Денежные потоки'!M2:M181) -> 1.3611905e+08
A22: СТРУКТУРА ФИНАНСИРОВАНИЯ
A23: Собственные средства | B23: руб. | C23: =Параметры!$C$23 -> 35000000
A24: Кредит | B24: руб. | C24: =Параметры!$C$22 -> 65000000
A25: Итого инвестиций | B25: руб. | C25: =Параметры!$C$5 -> 100000000

Sheet Чувствительность
A1: АНАЛИЗ ЧУВСТВИТЕЛЬНОСТИ
A3: Параметр | B3: Пессимист (−20%) | C3: Базовый | D3: Оптимист (+20%) | E3: Влияние на проект
A4: Себестоимость строительства, руб. | B4: =Параметры!$C$5*1.2 -> 120000000 | C4: =Параметры!$C$5 -> 100000000 | D4: =Параметры!$C$5*0.8 -> 80000000 | E4: Рост затрат → ↓ NPV, ↑ срок окупаемости
A5: Арендная ставка, руб./кв.м./мес. | B5: =Параметры!$C$7*0.8 -> 1171.2 | C5: =Параметры!$C$7 -> 1464 | D5: =Параметры!$C$7*1.2 -> 1756.8 | E5: Снижение ставки → ↓ выручки, ↓ NPV
A6: Кредитная ставка | B6: =Параметры!$C$10*1.2 -> 0.24 | C6: =Параметры!$C$10 -> 0.2 | D6: =Параметры!$C$10*0.8 -> 0.16 | E6: Рост ставки → ↑ процентов, ↓ чистой прибыли
A7: Инфляция (индексация аренды) | B7: =Параметры!$C$8*0.8 -> 0.064 | C7: =Параметры!$C$8 -> 0.08 | D7: =Параметры!$C$8*1.2 -> 0.096 | E7: Рост инфляции → ↑ выручки в будущем
A8: Ставка ЦБ (дисконтирование) | B8: =Параметры!$C$9*1.2 -> 0.174 | C8: =Параметры!$C$9 -> 0.145 | D8: =Параметры!$C$9*0.8 -> 0.116 | E8: Рост ставки → ↓ NPV (сильнее дисконт)
A11: БАЗОВЫЕ KPI (ссылки на лист «ИТОГ»)
A12: NPV | B12: руб. | C12: =ИТОГ!$C$6 -> 11126182
A13: IRR (годовая) | B13: % | C13: =ИТОГ!$C$7 -> 0.20966907
A14: ROI | B14: % | C14: =ИТОГ!$C$8 -> 9.4665412
A15: Срок окупаемости | B15: мес. | C15: =ИТОГ!$C$9 -> 86
A17: КАК ИСПОЛЬЗОВАТЬ ЭТУ ТАБЛИЦУ
A18: 1. Измените интересующий параметр на листе «Параметры» (синие ячейки C4:C17)
A19: 2. Excel автоматически пересчитает базовый и сценарные значения здесь
A20: 3. Откройте лист «ИТОГ» — посмотрите новые NPV, IRR, ROI
A21: 4. Для полной таблицы NPV по сценариям используйте Данные → Анализ «что если» → Таблица данных
