Workbook

Sheet Параметры
A1: ВХОДНЫЕ ПАРАМЕТРЫ ПРОЕКТА
A2: Название проекта | C2: Склад_Челябинск
A3: Дата начала строительства | B3: ГГГГ-ММ | C3: 2026-07
A4: Площадь объекта | B4: кв.м. | C4: 5000
A5: Себестоимость строительства (с НДС) | B5: руб. | C5: 200000000
A6: Доля кредита | C6: 0.7
A7: Арендная ставка | B7: руб./кв.м./мес. | C7: =1100*(1+C13) -> 1342
A8: Годовая инфляция (индексация аренды) | C8: 0.07
A9: Ставка ЦБ (ставка дисконтирования) | C9: 0.145
A10: Кредитная ставка | C10: 0.2
A11: Срок строительства | B11: мес. | C11: 12
A12: Горизонт планирования | B12: мес. | C12: 120
A13: Ставка НДС | C13: 0.22
A14: Ставка налога на прибыль | C14: 0.2
A15: Ставка налога на имущество | B15: в год | C15: 0.022
A16: Операционные расходы | B16: % от выручки б/НДС | C16: 0.1
A17: Срок полезного использования | B17: лет | C17: 20
A18: РАСЧЁТНЫЕ (ПРОИЗВОДНЫЕ) ПАРАМЕТРЫ
A19: Изменяйте только синие ячейки выше — формулы ниже пересчитаются автоматически.
A20: Себестоимость без НДС | B20: руб. | C20: =C5/(1+C13) -> 1.6393443e+08
A21: НДС строительства | B21: руб. | C21: =C5-C20 -> 36065574
A22: Сумма кредита | B22: руб. | C22: =C5*C6 -> 140000000
A23: Собственные средства | B23: руб. | C23: =C5*(1-C6) -> 60000000
A24: Стоимость 1 кв.м. | B24: руб. | C24: =C5/C4 -> 40000
A25: Период эксплуатации | B25: мес. | C25: =C12-C11 -> 108
A26: Аннуитетный платёж (в мес.) | B26: руб./мес. | C26: =-PMT(C10/12,C12-C11,C5*C6) -> 2803710.2
A27: Амортизация (в мес.) | B27: руб./мес. | C27: =C20/(C17*12) -> 683060.11
A28: НДС к возмещению (1-3 мес. экспл.) | B28: руб./мес. | C28: =(C5-C5/(1+C13))/3 -> 12021858

Sheet Денежные потоки
A1: Мес. | B1: Дата | C1: Фаза | D1: Выручка с НДС | E1: Выручка без НДС | F1: НДС выходной | G1: НДС входной | H1: НДС нетто | I1: Опер. расходы | J1: Амортизация | K1: Налог на имущ. | L1: EBIT | M1: Проценты | N1: EBT | O1: Налог на прибыль | P1: Чистая прибыль | Q1: Капвложения | R1: Транш кредита | S1: Погашение кредита | T1: Остаток кредита | U1: CF инвестора | V1: Накопл. CF
A2: 1 | B2: 2026-02 | C2: Строительство | D2: 0 | E2: 0 | F2: 0 | G2: 0 | H2: 0 | I2: 0 | J2: 0 | K2: 0 | L2: 0 | M2: =T2*Параметры!$C$10/12 -> 194444.44 | N2: =-M2 -> -194444.44 | O2: 0 | P2: 0 | Q2: =Параметры!$C$5/Параметры!$C$11 -> 16666667 | R2: =Параметры!$C$22/Параметры!$C$11 -> 11666667 | S2: 0 | T2: =Параметры!$C$22/Параметры!$C$11*A2 -> 11666667 | U2: =-(Параметры!$C$23/Параметры!$C$11+M2) -> -5194444.4 | V2: =U2 -> -5194444.4
A3: 2 | B3: 2026-03 | C3: Строительство | D3: 0 | E3: 0 | F3: 0 | G3: 0 | H3: 0 | I3: 0 | J3: 0 | K3: 0 | L3: 0 | M3: =T3*Параметры!$C$10/12 -> 388888.89 | N3: =-M3 -> -388888.89 | O3: 0 | P3: 0 | Q3: =Параметры!$C$5/Параметры!$C$11 -> 16666667 | R3: =Параметры!$C$22/Параметры!$C$11 -> 11666667 | S3: 0 | T3: =Параметры!$C$22/Параметры!$C$11*A3 -> 23333333 | U3: =-(Параметры!$C$23/Параметры!$C$11+M3) -> -5388888.9 | V3: =V2+U3 -> -10583333
A4: 3 | B4: 2026-04 | C4: Строительство | D4: 0 | E4: 0 | F4: 0 | G4: 0 | H4: 0 | I4: 0 | J4: 0 | K4: 0 | L4: 0 | M4: =T4*Параметры!$C$10/12 -> 583333.33 | N4: =-M4 -> -583333.33 | O4: 0 | P4: 0 | Q4: =Параметры!$C$5/Параметры!$C$11 -> 16666667 | R4: =Параметры!$C$22/Параметры!$C$11 -> 11666667 | S4: 0 | T4: =Параметры!$C$22/Параметры!$C$11*A4 -> 35000000 | U4: =-(Параметры!$C$23/Параметры!$C$11+M4) -> -5583333.3 | V4: =V3+U4 -> -16166667
A5: 4 | B5: 2026-05 | C5: Строительство | D5: 0 | E5: 0 | F5: 0 | G5: 0 | H5: 0 | I5: 0 | J5: 0 | K5: 0 | L5: 0 | M5: =T5*Параметры!$C$10/12 -> 777777.78 | N5: =-M5 -> -777777.78 | O5: 0 | P5: 0 | Q5: =Параметры!$C$5/Параметры!$C$11 -> 16666667 | R5: =Параметры!$C$22/Параметры!$C$11 -> 11666667 | S5: 0 | T5: =Параметры!$C$22/Параметры!$C$11*A5 -> 46666667 | U5: =-(Параметры!$C$23/Параметры!$C$11+M5) -> -5777777.8 | V5: =V4+U5 -> -21944444
A6: 5 | B6: 2026-06 | C6: Строительство | D6: 0 | E6: 0 | F6: 0 | G6: 0 | H6: 0 | I6: 0 | J6: 0 | K6: 0 | L6: 0 | M6: =T6*Параметры!$C$10/12 -> 972222.22 | N6: =-M6 -> -972222.22 | O6: 0 | P6: 0 | Q6: =Параметры!$C$5/Параметры!$C$11 -> 16666667 | R6: =Параметры!$C$22/Параметры!$C$11 -> 11666667 | S6: 0 | T6: =Параметры!$C$22/Параметры!$C$11*A6 -> 58333333 | U6: =-(Параметры!$C$23/Параметры!$C$11+M6) -> -5972222.2 | V6: =V5+U6 -> -27916667
A7: 6 | B7: 2026-07 | C7: Строительство | D7: 0 | E7: 0 | F7: 0 | G7: 0 | H7: 0 | I7: 0 | J7: 0 | K7: 0 | L7: 0 | M7: =T7*Параметры!$C$10/12 -> 1166666.7 | N7: =-M7 -> -1166666.7 | O7: 0 | P7: 0 | Q7: =Параметры!$C$5/Параметры!$C$11 -> 16666667 | R7: =Параметры!$C$22/Параметры!$C$11 -> 11666667 | S7: 0 | T7: =Параметры!$C$22/Параметры!$C$11*A7 -> 70000000 | U7: =-(Параметры!$C$23/Параметры!$C$11+M7) -> -6166666.7 | V7: =V6+U7 -> -34083333
A8: 7 | B8: 2026-08 | C8: Эксплуатация | D8: =Параметры!$C$4*Параметры!$C$7*(1+Параметры!$C$8)^INT((A8-Параметры!$C$11-1)/12) -> 6271028 | E8: =D8/(1+Параметры!$C$13) -> 5140186.9 | F8: =D8-E8 -> 1130841.1 | G8: =IF(AND(A8>Параметры!$C$11,A8<=Параметры!$C$11+3),Параметры!$C$28,0) -> 0 | H8: =F8-G8 -> 1130841.1 | I8: =E8*Параметры!$C$16 -> 514018.69 | J8: =Параметры!$C$27 -> 683060.11 | K8: =MAX(0,Параметры!$C$20-Параметры!$C$27*MAX(0,A8-Параметры!$C$11-1))*Параметры!$C$15/12 -> 300546.45 | L8: =E8-I8-J8-K8 -> 3642561.7 | M8: =T7*Параметры!$C$10/12 -> 1166666.7 | N8: =L8-M8 -> 2475895 | O8: =MAX(0,N8*Параметры!$C$14) -> 495179 | P8: =N8-O8 -> 1980716 | Q8: 0 | R8: 0 | S8: =MAX(0,MIN(Параметры!$C$26-M8,T7)) -> 1637043.6 | T8: =MAX(0,T7-S8) -> 68362956 | U8: =P8+J8-S8-H8 -> -104108.58 | V8: =V7+U8 -> -34187442
A9: 8 | B9: 2026-09 | C9: Эксплуатация | D9: =Параметры!$C$4*Параметры!$C$7*(1+Параметры!$C$8)^INT((A9-Параметры!$C$11-1)/12) -> 6271028 | E9: =D9/(1+Параметры!$C$13) -> 5140186.9 | F9: =D9-E9 -> 1130841.1 | G9: =IF(AND(A9>Параметры!$C$11,A9<=Параметры!$C$11+3),Параметры!$C$28,0) -> 0 | H9: =F9-G9 -> 1130841.1 | I9: =E9*Параметры!$C$16 -> 514018.69 | J9: =Параметры!$C$27 -> 683060.11 | K9: =MAX(0,Параметры!$C$20-Параметры!$C$27*MAX(0,A9-Параметры!$C$11-1))*Параметры!$C$15/12 -> 300546.45 | L9: =E9-I9-J9-K9 -> 3642561.7 | M9: =T8*Параметры!$C$10/12 -> 1139382.6 | N9: =L9-M9 -> 2503179.1 | O9: =MAX(0,N9*Параметры!$C$14) -> 500635.81 | P9: =N9-O9 -> 2002543.2 | Q9: 0 | R9: 0 | S9: =MAX(0,MIN(Параметры!$C$26-M9,T8)) -> 1664327.6 | T9: =MAX(0,T8-S9) -> 66698629 | U9: =P9+J9-S9-H9 -> -109565.39 | V9: =V8+U9 -> -34297007
A10: 9 | B10: 2026-10 | C10: Эксплуатация | D10: =Параметры!$C$4*Параметры!$C$7*(1+Параметры!$C$8)^INT((A10-Параметры!$C$11-1)/12) -> 6271028 | E10: =D10/(1+Параметры!$C$13) -> 5140186.9 | F10: =D10-E10 -> 1130841.1 | G10: =IF(AND(A10>Параметры!$C$11,A10<=Параметры!$C$11+3),Параметры!$C$28,0) -> 0 | H10: =F10-G10 -> 1130841.1 | I10: =E10*Параметры!$C$16 -> 514018.69 | J10: =Параметры!$C$27 -> 683060.11 | K10: =MAX(0,Параметры!$C$20-Параметры!$C$27*MAX(0,A10-Параметры!$C$11-1))*Параметры!$C$15/12 -> 300546.45 | L10: =E10-I10-J10-K10 -> 3642561.7 | M10: =T9*Параметры!$C$10/12 -> 1111643.8 | N10: =L10-M10 -> 2530917.9 | O10: =MAX(0,N10*Параметры!$C$14) -> 506183.57 | P10: =N10-O10 -> 2024734.3 | Q10: 0 | R10: 0 | S10: =MAX(0,MIN(Параметры!$C$26-M10,T9)) -> 1692066.4 | T10: =MAX(0,T9-S10) -> 65006562 | U10: =P10+J10-S10-H10 -> -115113.15 | V10: =V9+U10 -> -34412120
A11: 10 | B11: 2026-11 | C11: Эксплуатация | D11: =Параметры!$C$4*Параметры!$C$7*(1+Параметры!$C$8)^INT((A11-Параметры!$C$11-1)/12) -> 6271028 | E11: =D11/(1+Параметры!$C$13) -> 5140186.9 | F11: =D11-E11 -> 1130841.1 | G11: =IF(AND(A11>Параметры!$C$11,A11<=Параметры!$C$11+3),Параметры!$C$28,0) -> 0 | H11: =F11-G11 -> 1130841.1 | I11: =E11*Параметры!$C$16 -> 514018.69 | J11: =Параметры!$C$27 -> 683060.11 | K11: =MAX(0,Параметры!$C$20-Параметры!$C$27*MAX(0,A11-Параметры!$C$11-1))*Параметры!$C$15/12 -> 300546.45 | L11: =E11-I11-J11-K11 -> 3642561.7 | M11: =T10*Параметры!$C$10/12 -> 1083442.7 | N11: =L11-M11 -> 2559119 | O11: =MAX(0,N11*Параметры!$C$14) -> 511823.79 | P11: =N11-O11 -> 2047295.2 | Q11: 0 | R11: 0 | S11: =MAX(0,MIN(Параметры!$C$26-M11,T10)) -> 1720267.5 | T11: =MAX(0,T10-S11) -> 63286295 | U11: =P11+J11-S11-H11 -> -120753.37 | V11: =V10+U11 -> -34532874
A12: 11 | B12: 2026-12 | C12: Эксплуатация | D12: =Параметры!$C$4*Параметры!$C$7*(1+Параметры!$C$8)^INT((A12-Параметры!$C$11-1)/12) -> 6271028 | E12: =D12/(1+Параметры!$C$13) -> 5140186.9 | F12: =D12-E12 -> 1130841.1 | G12: =IF(AND(A12>Параметры!$C$11,A12<=Параметры!$C$11+3),Параметры!$C$28,0) -> 0 | H12: =F12-G12 -> 1130841.1 | I12: =E12*Параметры!$C$16 -> 514018.69 | J12: =Параметры!$C$27 -> 683060.11 | K12: =MAX(0,Параметры!$C$20-Параметры!$C$27*MAX(0,A12-Параметры!$C$11-1))*Параметры!$C$15/12 -> 300546.45 | L12: =E12-I12-J12-K12 -> 3642561.7 | M12: =T11*Параметры!$C$10/12 -> 1054771.6 | N12: =L12-M12 -> 2587790.1 | O12: =MAX(0,N12*Параметры!$C$14) -> 517558.02 | P12: =N12-O12 -> 2070232.1 | Q12: 0 | R12: 0 | S12: =MAX(0,MIN(Параметры!$C$26-M12,T11)) -> 1748938.7 | T12: =MAX(0,T11-S12) -> 61537356 | U12: =P12+J12-S12-H12 -> -126487.6 | V12: =V11+U12 -> -34659361
A13: 12 | B13: 2027-01 | C13: Эксплуатация | D13: =Параметры!$C$4*Параметры!$C$7*(1+Параметры!$C$8)^INT((A13-Параметры!$C$11-1)/12) -> 6271028 | E13: =D13/(1+Параметры!$C$13) -> 5140186.9 | F13: =D13-E13 -> 1130841.1 | G13: =IF(AND(A13>Параметры!$C$11,A13<=Параметры!$C$11+3),Параметры!$C$28,0) -> 0 | H13: =F13-G13 -> 1130841.1 | I13: =E13*Параметры!$C$16 -> 514018.69 | J13: =Параметры!$C$27 -> 683060.11 | K13: =MAX(0,Параметры!$C$20-Параметры!$C$27*MAX(0,A13-Параметры!$C$11-1))*Параметры!$C$15/12 -> 300546.45 | L13: =E13-I13-J13-K13 -> 3642561.7 | M13: =T12*Параметры!$C$10/12 -> 1025622.6 | N13: =L13-M13 -> 2616939.1 | O13: =MAX(0,N13*Параметры!$C$14) -> 523387.81 | P13: =N13-O13 -> 2093551.3 | Q13: 0 | R13: 0 | S13: =MAX(0,MIN(Параметры!$C$26-M13,T12)) -> 1778087.6 | T13: =MAX(0,T12-S13) -> 59759269 | U13: =P13+J13-S13-H13 -> -132317.39 | V13: =V12+U13 -> -34791679
A14: 13 | B14: 2027-02 | C14: Эксплуатация | D14: =Параметры!$C$4*Параметры!$C$7*(1+Параметры!$C$8)^INT((A14-Параметры!$C$11-1)/12) -> 6710000 | E14: =D14/(1+Параметры!$C$13) -> 5500000 | F14: =D14-E14 -> 1210000 | G14: =IF(AND(A14>Параметры!$C$11,A14<=Параметры!$C$11+3),Параметры!$C$28,0) -> 12021858 | H14: =F14-G14 -> -10811858 | I14: =E14*Параметры!$C$16 -> 550000 | J14: =Параметры!$C$27 -> 683060.11 | K14: =MAX(0,Параметры!$C$20-Параметры!$C$27*MAX(0,A14-Параметры!$C$11-1))*Параметры!$C$15/12 -> 300546.45 | L14: =E14-I14-J14-K14 -> 3966393.4 | M14: =T13*Параметры!$C$10/12 -> 995987.81 | N14: =L14-M14 -> 2970405.6 | O14: =MAX(0,N14*Параметры!$C$14) -> 594081.13 | P14: =N14-O14 -> 2376324.5 | Q14: 0 | R14: 0 | S14: =MAX(0,MIN(Параметры!$C$26-M14,T13)) -> 1807722.4 | T14: =MAX(0,T13-S14) -> 57951546 | U14: =P14+J14-S14-H14 -> 12063520 | V14: =V13+U14 -> -22728159
A15: 14 | B15: 2027-03 | C15: Эксплуатация | D15: =Параметры!$C$4*Параметры!$C$7*(1+Параметры!$C$8)^INT((A15-Параметры!$C$11-1)/12) -> 6710000 | E15: =D15/(1+Параметры!$C$13) -> 5500000 | F15: =D15-E15 -> 1210000 | G15: =IF(AND(A15>Параметры!$C$11,A15<=Параметры!$C$11+3),Параметры!$C$28,0) -> 12021858 | H15: =F15-G15 -> -10811858 | I15: =E15*Параметры!$C$16 -> 550000 | J15: =Параметры!$C$27 -> 683060.11 | K15: =MAX(0,Параметры!$C$20-Параметры!$C$27*MAX(0,A15-Параметры!$C$11-1))*Параметры!$C$15/12 -> 299294.17 | L15: =E15-I15-J15-K15 -> 3967645.7 | M15: =T14*Параметры!$C$10/12 -> 965859.1 | N15: =L15-M15 -> 3001786.6 | O15: =MAX(0,N15*Параметры!$C$14) -> 600357.32 | P15: =N15-O15 -> 2401429.3 | Q15: 0 | R15: 0 | S15: =MAX(0,MIN(Параметры!$C$26-M15,T14)) -> 1837851.1 | T15: =MAX(0,T14-S15) -> 56113695 | U15: =P15+J15-S15-H15 -> 12058496 | V15: =V14+U15 -> -10669663
A16: 15 | B16: 2027-04 | C16: Эксплуатация | D16: =Параметры!$C$4*Параметры!$C$7*(1+Параметры!$C$8)^INT((A16-Параметры!$C$11-1)/12) -> 6710000 | E16: =D16/(1+Параметры!$C$13) -> 5500000 | F16: =D16-E16 -> 1210000 | G16: =IF(AND(A16>Параметры!$C$11,A16<=Параметры!$C$11+3),Параметры!$C$28,0) -> 12021858 | H16: =F16-G16 -> -10811858 | I16: =E16*Параметры!$C$16 -> 550000 | J16: =Параметры!$C$27 -> 683060.11 | K16: =MAX(0,Параметры!$C$20-Параметры!$C$27*MAX(0,A16-Параметры!$C$11-1))*Параметры!$C$15/12 -> 298041.89 | L16: =E16-I16-J16-K16 -> 3968898 | M16: =T15*Параметры!$C$10/12 -> 935228.25 | N16: =L16-M16 -> 3033669.7 | O16: =MAX(0,N16*Параметры!$C$14) -> 606733.95 | P16: =N16-O16 -> 2426935.8 | Q16: 0 | R16: 0 | S16: =MAX(0,MIN(Параметры!$C$26-M16,T15)) -> 1868482 | T16: =MAX(0,T15-S16) -> 54245213 | U16: =P16+J16-S16-H16 -> 12053372 | V16: =V15+U16 -> 1383709.3
A17: 16 | B17: 2027-05 | C17: Эксплуатация | D17: =Параметры!$C$4*Параметры!$C$7*(1+Параметры!$C$8)^INT((A17-Параметры!$C$11-1)/12) -> 6710000 | E17: =D17/(1+Параметры!$C$13) -> 5500000 | F17: =D17-E17 -> 1210000 | G17: =IF(AND(A17>Параметры!$C$11,A17<=Параметры!$C$11+3),Параметры!$C$28,0) -> 0 | H17: =F17-G17 -> 1210000 | I17: =E17*Параметры!$C$16 -> 550000 | J17: =Параметры!$C$27 -> 683060.11 | K17: =MAX(0,Параметры!$C$20-Параметры!$C$27*MAX(0,A17-Параметры!$C$11-1))*Параметры!$C$15/12 -> 296789.62 | L17: =E17-I17-J17-K17 -> 3970150.3 | M17: =T16*Параметры!$C$10/12 -> 904086.88 | N17: =L17-M17 -> 3066063.4 | O17: =MAX(0,N17*Параметры!$C$14) -> 613212.68 | P17: =N17-O17 -> 2452850.7 | Q17: 0 | R17: 0 | S17: =MAX(0,MIN(Параметры!$C$26-M17,T16)) -> 1899623.4 | T17: =MAX(0,T16-S17) -> 52345590 | U17: =P17+J17-S17-H17 -> 26287.469 | V17: =V16+U17 -> 1409996.8
A18: 17 | B18: 2027-06 | C18: Эксплуатация | D18: =Параметры!$C$4*Параметры!$C$7*(1+Параметры!$C$8)^INT((A18-Параметры!$C$11-1)/12) -> 6710000 | E18: =D18/(1+Параметры!$C$13) -> 5500000 | F18: =D18-E18 -> 1210000 | G18: =IF(AND(A18>Параметры!$C$11,A18<=Параметры!$C$11+3),Параметры!$C$28,0) -> 0 | H18: =F18-G18 -> 1210000 | I18: =E18*Параметры!$C$16 -> 550000 | J18: =Параметры!$C$27 -> 683060.11 | K18: =MAX(0,Параметры!$C$20-Параметры!$C$27*MAX(0,A18-Параметры!$C$11-1))*Параметры!$C$15/12 -> 295537.34 | L18: =E18-I18-J18-K18 -> 3971402.6 | M18: =T17*Параметры!$C$10/12 -> 872426.49 | N18: =L18-M18 -> 3098976.1 | O18: =MAX(0,N18*Параметры!$C$14) -> 619795.21 | P18: =N18-O18 -> 2479180.8 | Q18: 0 | R18: 0 | S18: =MAX(0,MIN(Параметры!$C$26-M18,T17)) -> 1931283.7 | T18: =MAX(0,T17-S18) -> 50414306 | U18: =P18+J18-S18-H18 -> 20957.213 | V18: =V17+U18 -> 1430954
A19: 18 | B19: 2027-07 | C19: Эксплуатация | D19: =Параметры!$C$4*Параметры!$C$7*(1+Параметры!$C$8)^INT((A19-Параметры!$C$11-1)/12) -> 6710000 | E19: =D19/(1+Параметры!$C$13) -> 5500000 | F19: =D19-E19 -> 1210000 | G19: =IF(AND(A19>Параметры!$C$11,A19<=Параметры!$C$11+3),Параметры!$C$28,0) -> 0 | H19: =F19-G19 -> 1210000 | I19: =E19*Параметры!$C$16 -> 550000 | J19: =Параметры!$C$27 -> 683060.11 | K19: =MAX(0,Параметры!$C$20-Параметры!$C$27*MAX(0,A19-Параметры!$C$11-1))*Параметры!$C$15/12 -> 294285.06 | L19: =E19-I19-J19-K19 -> 3972654.8 | M19: =T18*Параметры!$C$10/12 -> 840238.43 | N19: =L19-M19 -> 3132416.4 | O19: =MAX(0,N19*Параметры!$C$14) -> 626483.28 | P19: =N19-O19 -> 2505933.1 | Q19: 0 | R19: 0 | S19: =MAX(0,MIN(Параметры!$C$26-M19,T18)) -> 1963471.8 | T19: =MAX(0,T18-S19) -> 48450834 | U19: =P19+J19-S19-H19 -> 15521.422 | V19: =V18+U19 -> 1446475.4
... A121: 120 | B121: 2036-01 | C121: Эксплуатация | D121: =Параметры!$C$4*Параметры!$C$7*(1+Параметры!$C$8)^INT((A121-Параметры!$C$11-1)/12) -> 11529029 | E121: =D121/(1+Параметры!$C$13) -> 9450024 | F121: =D121-E121 -> 2079005.3 | G121: =IF(AND(A121>Параметры!$C$11,A121<=Параметры!$C$11+3),Параметры!$C$28,0) -> 0 | H121: =F121-G121 -> 2079005.3 | I121: =E121*Параметры!$C$16 -> 945002.4 | J121: =Параметры!$C$27 -> 683060.11 | K121: =MAX(0,Параметры!$C$20-Параметры!$C$27*MAX(0,A121-Параметры!$C$11-1))*Параметры!$C$15/12 -> 166552.82 | L121: =E121-I121-J121-K121 -> 7655408.7 | M121: =T120*Параметры!$C$10/12 -> 0 | N121: =L121-M121 -> 7655408.7 | O121: =MAX(0,N121*Параметры!$C$14) -> 1531081.7 | P121: =N121-O121 -> 6124326.9 | Q121: 0 | R121: 0 | S121: =MAX(0,MIN(Параметры!$C$26-M121,T120)) -> 0 | T121: =MAX(0,T120-S121) -> 0 | U121: =P121+J121-S121-H121 -> 4728381.8 | V121: =V120+U121 -> 3.1961258e+08
A122: ИТОГО ЗА ГОРИЗОНТ | C122: =SUM(C2:C121) -> 0 | D122: =SUM(D2:D121) -> 1.0020938e+09 | E122: =SUM(E2:E121) -> 8.2138838e+08 | F122: =SUM(F2:F121) -> 1.8070544e+08 | G122: =SUM(G2:G121) -> 36065574 | H122: =SUM(H2:H121) -> 1.4463987e+08 | I122: =SUM(I2:I121) -> 82138838 | J122: =SUM(J2:J121) -> 77868852 | ... V122: =SUM(V2:V121) -> 1.1996569e+10

Sheet ИТОГ
A1: КЛЮЧЕВЫЕ ПОКАЗАТЕЛИ ПРОЕКТА
A2: Проект | C2: =Параметры!$C$2 -> Склад_Челябинск
A3: Дата начала | C3: =Параметры!$C$3 -> 2026-07
A4: Горизонт планирования | C4: =Параметры!$C$12&" мес." -> 120 мес.
A5: ПОКАЗАТЕЛИ ЭФФЕКТИВНОСТИ
A6: NPV (чистая приведённая стоимость) | B6: руб. | C6: =NPV(Параметры!$C$9/12,'Денежные потоки'!U2:U121) -> 1.201475e+08
A7: IRR (годовая внутренняя норма доходности) | B7: % | C7: =IFERROR((1+IRR('Денежные потоки'!U2:U121))^12-1,"Н/Д") -> 0.79052776
A8: ROI (рентабельность СС за горизонт) | B8: % | C8: =IFERROR(SUM('Денежные потоки'!P2:P121)/Параметры!$C$23,"Н/Д") -> 8.1744488
A9: Срок окупаемости | B9: мес. | C9: =IFERROR(MATCH(TRUE,'Денежные потоки'!V2:V121>=0,0),"Нет в горизонте") -> Нет в горизонте
A10: Ставка дисконтирования (ЦБ) | B10: % | C10: =Параметры!$C$9 -> 0.145
A11: ФИНАНСОВЫЕ ИТОГИ ЗА ГОРИЗОНТ
A12: Суммарная выручка (с НДС) | B12: руб. | C12: =SUM('Денежные потоки'!D2:D121) -> 1.0020938e+09
A13: Суммарная выручка (без НДС) | B13: руб. | C13: =SUM('Денежные потоки'!E2:E121) -> 8.2138838e+08
A14: Операционные расходы | B14: руб. | C14: =SUM('Денежные потоки'!I2:I121) -> 82138838
A15: Чистая прибыль (суммарно) | B15: руб. | C15: =SUM('Денежные потоки'!P2:P121) -> 4.9046693e+08
A16: НАЛОГИ И ПЛАТЕЖИ ЗА ГОРИЗОНТ
A17: Налог на прибыль | B17: руб. | C17: =SUM('Денежные потоки'!O2:O121) -> 1.2261673e+08
A18: НДС к уплате (выплаты в бюджет) | B18: руб. | C18: =SUMIF('Денежные потоки'!H2:H121,">0",'Денежные потоки'!H2:H121) -> 1.7707544e+08
A19: Возврат НДС из строительства | B19: руб. | C19: =SUM('Денежные потоки'!G2:G121) -> 36065574
A20: Налог на имущество | B20: руб. | C20: =SUM('Денежные потоки'!K2:K121) -> 27026639
A21: Проценты по кредиту | B21: руб. | C21: =SUM('Денежные потоки'!M2:M121) -> 25353721
A22: СТРУКТУРА ФИНАНСИРОВАНИЯ
A23: Собственные средства | B23: руб. | C23: =Параметры!$C$23 -> 60000000
A24: Кредит | B24: руб. | C24: =Параметры!$C$22 -> 140000000
A25: Итого инвестиций | B25: руб. | C25: =Параметры!$C$5 -> 200000000

Sheet Чувствительность
A1: АНАЛИЗ ЧУВСТВИТЕЛЬНОСТИ
F2: NPV базовый | G2: NPV оптимист
A3: Параметр | B3: Пессимист (−20%) | C3: Базовый | D3: Оптимист (+20%) | E3: Влияние на проект
A4: Себестоимость строительства, руб. | B4: =Параметры!$C$5*1.2 -> 240000000 | C4: =Параметры!$C$5 -> 200000000 | D4: =Параметры!$C$5*0.8 -> 160000000 | E4: Рост затрат → ↓ NPV
A5: Арендная ставка, руб./кв.м./мес. | B5: =Параметры!$C$7*0.8 -> 1073.6 | C5: =Параметры!$C$7 -> 1342 | D5: =Параметры!$C$7*1.2 -> 1610.4 | E5: Снижение ставки → ↓ выручки
A6: Кредитная ставка | B6: =Параметры!$C$10*1.2 -> 0.24 | C6: =Параметры!$C$10 -> 0.2 | D6: =Параметры!$C$10*0.8 -> 0.16 | E6: Рост ставки → ↑ процентов
A7: Инфляция (индексация аренды) | B7: =Параметры!$C$8*0.8 -> 0.056 | C7: =Параметры!$C$8 -> 0.07 | D7: =Параметры!$C$8*1.2 -> 0.084 | E7: Рост инфляции → ↑ выручки
A8: Ставка ЦБ (дисконтирование) | B8: =Параметры!$C$9*1.2 -> 0.174 | C8: =Параметры!$C$9 -> 0.145 | D8: =Параметры!$C$9*0.8 -> 0.116 | E8: Рост ставки → ↓ NPV
A10: БАЗОВЫЕ KPI (ссылки на ИТОГ)
A11: NPV | B11: руб. | C11: =ИТОГ!$C$6 -> 1.201475e+08
A12: IRR | B12: % | C12: =ИТОГ!$C$7 -> 0.79052776
A13: ROI | B13: % | C13: =ИТОГ!$C$8 -> 8.1744488
A14: Срок окупаемости | B14: мес. | C14: =ИТОГ!$C$9 -> Нет в горизонте
A16: Чтобы оценить конкретный сценарий — измените параметр на листе «Параметры»,
A17: Excel пересчитает модель и KPI на листе «ИТОГ».
