Workbook

Sheet Параметры
A1: ВХОДНЫЕ ПАРАМЕТРЫ ПРОЕКТА
A2: Название проекта | C2: Склад Весна
A3: Дата начала строительства | B3: ДД.ММ.ГГГГ | C3: 01.07.2026
A4: Площадь объекта | B4: кв.м. | C4: 1000
A5: Себестоимость строительства (с НДС) | B5: руб. | C5: 48800000
A6: Доля кредита | C6: 0.8
A7: Арендная ставка | B7: руб./кв.м./мес. | C7: 1190.72
A8: Годовая инфляция (индексация аренды) | C8: 0.05
A9: Ставка ЦБ (ставка дисконтирования) | C9: 0.145
A10: Кредитная ставка | C10: 0.2
A11: Срок строительства | B11: мес. | C11: 6
A12: Горизонт планирования | B12: мес. | C12: 120
A13: Ставка НДС | C13: 0.22
A14: Ставка налога на прибыль | C14: 0.25
A15: Ставка налога на имущество | B15: в год | C15: 0.022
A16: Операционные расходы | B16: % от выручки б/НДС | C16: 0.1
A17: Срок полезного использования | B17: лет | C17: 20
A18: РАСЧЁТНЫЕ (ПРОИЗВОДНЫЕ) ПАРАМЕТРЫ
A19: Изменяйте только синие ячейки выше — формулы ниже пересчитаются автоматически.
A20: Себестоимость без НДС | B20: руб. | C20: =C5/(1+C13)
A21: НДС строительства | B21: руб. | C21: =C5-C20
A22: Сумма кредита | B22: руб. | C22: =C5*C6
A23: Собственные средства | B23: руб. | C23: =C5*(1-C6)
A24: Стоимость 1 кв.м. | B24: руб. | C24: =C5/C4
A25: Период эксплуатации | B25: мес. | C25: =C12-C11
A26: Аннуитетный платёж (в мес.) | B26: руб./мес. | C26: =-PMT(C10/12,C12-C11,C5*C6)
A27: Амортизация (в мес.) | B27: руб./мес. | C27: =C20/(C17*12)
A28: НДС к возмещению (1-3 мес. экспл.) | B28: руб./мес. | C28: =(C5-C5/(1+C13))/3

Sheet Денежные потоки
A1: Мес. | B1: Дата | C1: Фаза | D1: Выручка с НДС | E1: Выручка без НДС | F1: НДС выходной | G1: НДС входной | H1: НДС нетто | I1: Опер. расходы | J1: Амортизация | K1: Налог на имущ. | L1: EBIT | M1: Проценты | N1: EBT | O1: Налог на прибыль | P1: Чистая прибыль | Q1: Капвложения | R1: Транш кредита | S1: Погашение кредита | T1: Остаток кредита | U1: CF инвестора | V1: Накопл. CF
A2: 1 | B2: 01.08.2026 | C2: Строительство | D2: 0 | E2: 0 | F2: 0 | G2: 0 | H2: 0 | I2: 0 | J2: 0 | K2: 0 | L2: 0 | M2: =T2*'Параметры'!$C$10/12 | N2: =-M2 | O2: 0 | P2: 0 | Q2: ='Параметры'!$C$5/'Параметры'!$C$11 | R2: ='Параметры'!$C$22/'Параметры'!$C$11 | S2: 0 | T2: ='Параметры'!$C$22/'Параметры'!$C$11*A2 | U2: =-('Параметры'!$C$23/'Параметры'!$C$11+M2) | V2: =U2
A3: 2 | B3: 01.09.2026 | C3: Строительство | D3: 0 | E3: 0 | F3: 0 | G3: 0 | H3: 0 | I3: 0 | J3: 0 | K3: 0 | L3: 0 | M3: =T3*'Параметры'!$C$10/12 | N3: =-M3 | O3: 0 | P3: 0 | Q3: ='Параметры'!$C$5/'Параметры'!$C$11 | R3: ='Параметры'!$C$22/'Параметры'!$C$11 | S3: 0 | T3: ='Параметры'!$C$22/'Параметры'!$C$11*A3 | U3: =-('Параметры'!$C$23/'Параметры'!$C$11+M3) | V3: =V2+U3
A4: 3 | B4: 01.10.2026 | C4: Строительство | D4: 0 | E4: 0 | F4: 0 | G4: 0 | H4: 0 | I4: 0 | J4: 0 | K4: 0 | L4: 0 | M4: =T4*'Параметры'!$C$10/12 | N4: =-M4 | O4: 0 | P4: 0 | Q4: ='Параметры'!$C$5/'Параметры'!$C$11 | R4: ='Параметры'!$C$22/'Параметры'!$C$11 | S4: 0 | T4: ='Параметры'!$C$22/'Параметры'!$C$11*A4 | U4: =-('Параметры'!$C$23/'Параметры'!$C$11+M4) | V4: =V3+U4
A5: 4 | B5: 01.11.2026 | C5: Строительство | D5: 0 | E5: 0 | F5: 0 | G5: 0 | H5: 0 | I5: 0 | J5: 0 | K5: 0 | L5: 0 | M5: =T5*'Параметры'!$C$10/12 | N5: =-M5 | O5: 0 | P5: 0 | Q5: ='Параметры'!$C$5/'Параметры'!$C$11 | R5: ='Параметры'!$C$22/'Параметры'!$C$11 | S5: 0 | T5: ='Параметры'!$C$22/'Параметры'!$C$11*A5 | U5: =-('Параметры'!$C$23/'Параметры'!$C$11+M5) | V5: =V4+U5
A6: 5 | B6: 01.12.2026 | C6: Строительство | D6: 0 | E6: 0 | F6: 0 | G6: 0 | H6: 0 | I6: 0 | J6: 0 | K6: 0 | L6: 0 | M6: =T6*'Параметры'!$C$10/12 | N6: =-M6 | O6: 0 | P6: 0 | Q6: ='Параметры'!$C$5/'Параметры'!$C$11 | R6: ='Параметры'!$C$22/'Параметры'!$C$11 | S6: 0 | T6: ='Параметры'!$C$22/'Параметры'!$C$11*A6 | U6: =-('Параметры'!$C$23/'Параметры'!$C$11+M6) | V6: =V5+U6
A7: 6 | B7: 01.01.2027 | C7: Строительство | D7: 0 | E7: 0 | F7: 0 | G7: 0 | H7: 0 | I7: 0 | J7: 0 | K7: 0 | L7: 0 | M7: =T7*'Параметры'!$C$10/12 | N7: =-M7 | O7: 0 | P7: 0 | Q7: ='Параметры'!$C$5/'Параметры'!$C$11 | R7: ='Параметры'!$C$22/'Параметры'!$C$11 | S7: 0 | T7: ='Параметры'!$C$22/'Параметры'!$C$11*A7 | U7: =-('Параметры'!$C$23/'Параметры'!$C$11+M7) | V7: =V6+U7
A8: 7 | B8: 01.02.2027 | C8: Эксплуатация | D8: ='Параметры'!$C$4*'Параметры'!$C$7*(1+'Параметры'!$C$8)^INT((A8-'Параметры'!$C$11-1)/12) | E8: =D8/(1+'Параметры'!$C$13) | F8: =D8-E8 | G8: =IF(AND(A8>'Параметры'!$C$11,A8<='Параметры'!$C$11+3),'Параметры'!$C$28,0) | H8: =F8-G8 | I8: =E8*'Параметры'!$C$16 | J8: ='Параметры'!$C$27 | K8: =MAX(0,'Параметры'!$C$20-'Параметры'!$C$27*MAX(0,A8-'Параметры'!$C$11-1))*'Параметры'!$C$15/12 | L8: =E8-I8-J8-K8 | M8: =T7*'Параметры'!$C$10/12 | N8: =L8-M8 | O8: =MAX(0,N8*'Параметры'!$C$14) | P8: =N8-O8 | Q8: 0 | R8: 0 | S8: =MAX(0,MIN('Параметры'!$C$26-M8,T7)) | T8: =MAX(0,T7-S8) | U8: =P8+J8-S8-H8 | V8: =V7+U8
A9: 8 | B9: 01.03.2027 | C9: Эксплуатация | D9: ='Параметры'!$C$4*'Параметры'!$C$7*(1+'Параметры'!$C$8)^INT((A9-'Параметры'!$C$11-1)/12) | E9: =D9/(1+'Параметры'!$C$13) | F9: =D9-E9 | G9: =IF(AND(A9>'Параметры'!$C$11,A9<='Параметры'!$C$11+3),'Параметры'!$C$28,0) | H9: =F9-G9 | I9: =E9*'Параметры'!$C$16 | J9: ='Параметры'!$C$27 | K9: =MAX(0,'Параметры'!$C$20-'Параметры'!$C$27*MAX(0,A9-'Параметры'!$C$11-1))*'Параметры'!$C$15/12 | L9: =E9-I9-J9-K9 | M9: =T8*'Параметры'!$C$10/12 | N9: =L9-M9 | O9: =MAX(0,N9*'Параметры'!$C$14) | P9: =N9-O9 | Q9: 0 | R9: 0 | S9: =MAX(0,MIN('Параметры'!$C$26-M9,T8)) | T9: =MAX(0,T8-S9) | U9: =P9+J9-S9-H9 | V9: =V8+U9
A10: 9 | B10: 01.04.2027 | C10: Эксплуатация | D10: ='Параметры'!$C$4*'Параметры'!$C$7*(1+'Параметры'!$C$8)^INT((A10-'Параметры'!$C$11-1)/12) | E10: =D10/(1+'Параметры'!$C$13) | F10: =D10-E10 | G10: =IF(AND(A10>'Параметры'!$C$11,A10<='Параметры'!$C$11+3),'Параметры'!$C$28,0) | H10: =F10-G10 | I10: =E10*'Параметры'!$C$16 | J10: ='Параметры'!$C$27 | K10: =MAX(0,'Параметры'!$C$20-'Параметры'!$C$27*MAX(0,A10-'Параметры'!$C$11-1))*'Параметры'!$C$15/12 | L10: =E10-I10-J10-K10 | M10: =T9*'Параметры'!$C$10/12 | N10: =L10-M10 | O10: =MAX(0,N10*'Параметры'!$C$14) | P10: =N10-O10 | Q10: 0 | R10: 0 | S10: =MAX(0,MIN('Параметры'!$C$26-M10,T9)) | T10: =MAX(0,T9-S10) | U10: =P10+J10-S10-H10 | V10: =V9+U10
A11: 10 | B11: 01.05.2027 | C11: Эксплуатация | D11: ='Параметры'!$C$4*'Параметры'!$C$7*(1+'Параметры'!$C$8)^INT((A11-'Параметры'!$C$11-1)/12) | E11: =D11/(1+'Параметры'!$C$13) | F11: =D11-E11 | G11: =IF(AND(A11>'Параметры'!$C$11,A11<='Параметры'!$C$11+3),'Параметры'!$C$28,0) | H11: =F11-G11 | I11: =E11*'Параметры'!$C$16 | J11: ='Параметры'!$C$27 | K11: =MAX(0,'Параметры'!$C$20-'Параметры'!$C$27*MAX(0,A11-'Параметры'!$C$11-1))*'Параметры'!$C$15/12 | L11: =E11-I11-J11-K11 | M11: =T10*'Параметры'!$C$10/12 | N11: =L11-M11 | O11: =MAX(0,N11*'Параметры'!$C$14) | P11: =N11-O11 | Q11: 0 | R11: 0 | S11: =MAX(0,MIN('Параметры'!$C$26-M11,T10)) | T11: =MAX(0,T10-S11) | U11: =P11+J11-S11-H11 | V11: =V10+U11
A12: 11 | B12: 01.06.2027 | C12: Эксплуатация | D12: ='Параметры'!$C$4*'Параметры'!$C$7*(1+'Параметры'!$C$8)^INT((A12-'Параметры'!$C$11-1)/12) | E12: =D12/(1+'Параметры'!$C$13) | F12: =D12-E12 | G12: =IF(AND(A12>'Параметры'!$C$11,A12<='Параметры'!$C$11+3),'Параметры'!$C$28,0) | H12: =F12-G12 | I12: =E12*'Параметры'!$C$16 | J12: ='Параметры'!$C$27 | K12: =MAX(0,'Параметры'!$C$20-'Параметры'!$C$27*MAX(0,A12-'Параметры'!$C$11-1))*'Параметры'!$C$15/12 | L12: =E12-I12-J12-K12 | M12: =T11*'Параметры'!$C$10/12 | N12: =L12-M12 | O12: =MAX(0,N12*'Параметры'!$C$14) | P12: =N12-O12 | Q12: 0 | R12: 0 | S12: =MAX(0,MIN('Параметры'!$C$26-M12,T11)) | T12: =MAX(0,T11-S12) | U12: =P12+J12-S12-H12 | V12: =V11+U12
A13: 12 | B13: 01.07.2027 | C13: Эксплуатация | D13: ='Параметры'!$C$4*'Параметры'!$C$7*(1+'Параметры'!$C$8)^INT((A13-'Параметры'!$C$11-1)/12) | E13: =D13/(1+'Параметры'!$C$13) | F13: =D13-E13 | G13: =IF(AND(A13>'Параметры'!$C$11,A13<='Параметры'!$C$11+3),'Параметры'!$C$28,0) | H13: =F13-G13 | I13: =E13*'Параметры'!$C$16 | J13: ='Параметры'!$C$27 | K13: =MAX(0,'Параметры'!$C$20-'Параметры'!$C$27*MAX(0,A13-'Параметры'!$C$11-1))*'Параметры'!$C$15/12 | L13: =E13-I13-J13-K13 | M13: =T12*'Параметры'!$C$10/12 | N13: =L13-M13 | O13: =MAX(0,N13*'Параметры'!$C$14) | P13: =N13-O13 | Q13: 0 | R13: 0 | S13: =MAX(0,MIN('Параметры'!$C$26-M13,T12)) | T13: =MAX(0,T12-S13) | U13: =P13+J13-S13-H13 | V13: =V12+U13
A14: 13 | B14: 01.08.2027 | C14: Эксплуатация | D14: ='Параметры'!$C$4*'Параметры'!$C$7*(1+'Параметры'!$C$8)^INT((A14-'Параметры'!$C$11-1)/12) | E14: =D14/(1+'Параметры'!$C$13) | F14: =D14-E14 | G14: =IF(AND(A14>'Параметры'!$C$11,A14<='Параметры'!$C$11+3),'Параметры'!$C$28,0) | H14: =F14-G14 | I14: =E14*'Параметры'!$C$16 | J14: ='Параметры'!$C$27 | K14: =MAX(0,'Параметры'!$C$20-'Параметры'!$C$27*MAX(0,A14-'Параметры'!$C$11-1))*'Параметры'!$C$15/12 | L14: =E14-I14-J14-K14 | M14: =T13*'Параметры'!$C$10/12 | N14: =L14-M14 | O14: =MAX(0,N14*'Параметры'!$C$14) | P14: =N14-O14 | Q14: 0 | R14: 0 | S14: =MAX(0,MIN('Параметры'!$C$26-M14,T13)) | T14: =MAX(0,T13-S14) | U14: =P14+J14-S14-H14 | V14: =V13+U14
A15: 14 | B15: 01.09.2027 | C15: Эксплуатация | D15: ='Параметры'!$C$4*'Параметры'!$C$7*(1+'Параметры'!$C$8)^INT((A15-'Параметры'!$C$11-1)/12) | E15: =D15/(1+'Параметры'!$C$13) | F15: =D15-E15 | G15: =IF(AND(A15>'Параметры'!$C$11,A15<='Параметры'!$C$11+3),'Параметры'!$C$28,0) | H15: =F15-G15 | I15: =E15*'Параметры'!$C$16 | J15: ='Параметры'!$C$27 | K15: =MAX(0,'Параметры'!$C$20-'Параметры'!$C$27*MAX(0,A15-'Параметры'!$C$11-1))*'Параметры'!$C$15/12 | L15: =E15-I15-J15-K15 | M15: =T14*'Параметры'!$C$10/12 | N15: =L15-M15 | O15: =MAX(0,N15*'Параметры'!$C$14) | P15: =N15-O15 | Q15: 0 | R15: 0 | S15: =MAX(0,MIN('Параметры'!$C$26-M15,T14)) | T15: =MAX(0,T14-S15) | U15: =P15+J15-S15-H15 | V15: =V14+U15
A16: 15 | B16: 01.10.2027 | C16: Эксплуатация | D16: ='Параметры'!$C$4*'Параметры'!$C$7*(1+'Параметры'!$C$8)^INT((A16-'Параметры'!$C$11-1)/12) | E16: =D16/(1+'Параметры'!$C$13) | F16: =D16-E16 | G16: =IF(AND(A16>'Параметры'!$C$11,A16<='Параметры'!$C$11+3),'Параметры'!$C$28,0) | H16: =F16-G16 | I16: =E16*'Параметры'!$C$16 | J16: ='Параметры'!$C$27 | K16: =MAX(0,'Параметры'!$C$20-'Параметры'!$C$27*MAX(0,A16-'Параметры'!$C$11-1))*'Параметры'!$C$15/12 | L16: =E16-I16-J16-K16 | M16: =T15*'Параметры'!$C$10/12 | N16: =L16-M16 | O16: =MAX(0,N16*'Параметры'!$C$14) | P16: =N16-O16 | Q16: 0 | R16: 0 | S16: =MAX(0,MIN('Параметры'!$C$26-M16,T15)) | T16: =MAX(0,T15-S16) | U16: =P16+J16-S16-H16 | V16: =V15+U16
A17: 16 | B17: 01.11.2027 | C17: Эксплуатация | D17: ='Параметры'!$C$4*'Параметры'!$C$7*(1+'Параметры'!$C$8)^INT((A17-'Параметры'!$C$11-1)/12) | E17: =D17/(1+'Параметры'!$C$13) | F17: =D17-E17 | G17: =IF(AND(A17>'Параметры'!$C$11,A17<='Параметры'!$C$11+3),'Параметры'!$C$28,0) | H17: =F17-G17 | I17: =E17*'Параметры'!$C$16 | J17: ='Параметры'!$C$27 | K17: =MAX(0,'Параметры'!$C$20-'Параметры'!$C$27*MAX(0,A17-'Параметры'!$C$11-1))*'Параметры'!$C$15/12 | L17: =E17-I17-J17-K17 | M17: =T16*'Параметры'!$C$10/12 | N17: =L17-M17 | O17: =MAX(0,N17*'Параметры'!$C$14) | P17: =N17-O17 | Q17: 0 | R17: 0 | S17: =MAX(0,MIN('Параметры'!$C$26-M17,T16)) | T17: =MAX(0,T16-S17) | U17: =P17+J17-S17-H17 | V17: =V16+U17
A18: 17 | B18: 01.12.2027 | C18: Эксплуатация | D18: ='Параметры'!$C$4*'Параметры'!$C$7*(1+'Параметры'!$C$8)^INT((A18-'Параметры'!$C$11-1)/12) | E18: =D18/(1+'Параметры'!$C$13) | F18: =D18-E18 | G18: =IF(AND(A18>'Параметры'!$C$11,A18<='Параметры'!$C$11+3),'Параметры'!$C$28,0) | H18: =F18-G18 | I18: =E18*'Параметры'!$C$16 | J18: ='Параметры'!$C$27 | K18: =MAX(0,'Параметры'!$C$20-'Параметры'!$C$27*MAX(0,A18-'Параметры'!$C$11-1))*'Параметры'!$C$15/12 | L18: =E18-I18-J18-K18 | M18: =T17*'Параметры'!$C$10/12 | N18: =L18-M18 | O18: =MAX(0,N18*'Параметры'!$C$14) | P18: =N18-O18 | Q18: 0 | R18: 0 | S18: =MAX(0,MIN('Параметры'!$C$26-M18,T17)) | T18: =MAX(0,T17-S18) | U18: =P18+J18-S18-H18 | V18: =V17+U18
A19: 18 | B19: 01.01.2028 | C19: Эксплуатация | D19: ='Параметры'!$C$4*'Параметры'!$C$7*(1+'Параметры'!$C$8)^INT((A19-'Параметры'!$C$11-1)/12) | E19: =D19/(1+'Параметры'!$C$13) | F19: =D19-E19 | G19: =IF(AND(A19>'Параметры'!$C$11,A19<='Параметры'!$C$11+3),'Параметры'!$C$28,0) | H19: =F19-G19 | I19: =E19*'Параметры'!$C$16 | J19: ='Параметры'!$C$27 | K19: =MAX(0,'Параметры'!$C$20-'Параметры'!$C$27*MAX(0,A19-'Параметры'!$C$11-1))*'Параметры'!$C$15/12 | L19: =E19-I19-J19-K19 | M19: =T18*'Параметры'!$C$10/12 | N19: =L19-M19 | O19: =MAX(0,N19*'Параметры'!$C$14) | P19: =N19-O19 | Q19: 0 | R19: 0 | S19: =MAX(0,MIN('Параметры'!$C$26-M19,T18)) | T19: =MAX(0,T18-S19) | U19: =P19+J19-S19-H19 | V19: =V18+U19
... A121: 120 | B121: 01.07.2036 | C121: Эксплуатация | D121: ='Параметры'!$C$4*'Параметры'!$C$7*(1+'Параметры'!$C$8)^INT((A121-'Параметры'!$C$11-1)/12) | E121: =D121/(1+'Параметры'!$C$13) | F121: =D121-E121 | G121: =IF(AND(A121>'Параметры'!$C$11,A121<='Параметры'!$C$11+3),'Параметры'!$C$28,0) | H121: =F121-G121 | I121: =E121*'Параметры'!$C$16 | J121: ='Параметры'!$C$27 | K121: =MAX(0,'Параметры'!$C$20-'Параметры'!$C$27*MAX(0,A121-'Параметры'!$C$11-1))*'Параметры'!$C$15/12 | L121: =E121-I121-J121-K121 | M121: =T120*'Параметры'!$C$10/12 | N121: =L121-M121 | O121: =MAX(0,N121*'Параметры'!$C$14) | P121: =N121-O121 | Q121: 0 | R121: 0 | S121: =MAX(0,MIN('Параметры'!$C$26-M121,T120)) | T121: =MAX(0,T120-S121) | U121: =P121+J121-S121-H121 | V121: =V120+U121
A122: ИТОГО ЗА ГОРИЗОНТ | C122: =SUM(C2:C121) | D122: =SUM(D2:D121) | E122: =SUM(E2:E121) | F122: =SUM(F2:F121) | G122: =SUM(G2:G121) | H122: =SUM(H2:H121) | I122: =SUM(I2:I121) | J122: =SUM(J2:J121) | ... V122: =SUM(V2:V121)

Sheet ИТОГ
A1: КЛЮЧЕВЫЕ ПОКАЗАТЕЛИ ПРОЕКТА
A2: Проект | C2: ='Параметры'!$C$2
A3: Дата начала | C3: ='Параметры'!$C$3
A4: Горизонт планирования | C4: ='Параметры'!$C$12&" мес."
A5: ПОКАЗАТЕЛИ ЭФФЕКТИВНОСТИ
A6: NPV (чистая приведённая стоимость) | B6: руб. | C6: =NPV('Параметры'!$C$9/12,'Денежные потоки'!U2:U121)
A7: IRR (годовая внутренняя норма доходности) | B7: % | C7: =IFERROR((1+IRR('Денежные потоки'!U2:U121))^12-1,"Н/Д")
A8: ROI (рентабельность СС за горизонт) | B8: % | C8: =IFERROR(SUM('Денежные потоки'!P2:P121)/'Параметры'!$C$23,"Н/Д")
A9: Срок окупаемости | B9: мес. | C9: =MATCH(TRUE,'Денежные потоки'!V2:V121>=0,0)
A10: Ставка дисконтирования (ЦБ) | B10: % | C10: ='Параметры'!$C$9
A11: ФИНАНСОВЫЕ ИТОГИ ЗА ГОРИЗОНТ
A12: Суммарная выручка (с НДС) | B12: руб. | C12: =SUM('Денежные потоки'!D2:D121)
A13: Суммарная выручка (без НДС) | B13: руб. | C13: =SUM('Денежные потоки'!E2:E121)
A14: Операционные расходы | B14: руб. | C14: =SUM('Денежные потоки'!I2:I121)
A15: Чистая прибыль (суммарно) | B15: руб. | C15: =SUM('Денежные потоки'!P2:P121)
A16: НАЛОГИ И ПЛАТЕЖИ ЗА ГОРИЗОНТ
A17: Налог на прибыль | B17: руб. | C17: =SUM('Денежные потоки'!O2:O121)
A18: НДС к уплате (выплаты в бюджет) | B18: руб. | C18: =SUMIF('Денежные потоки'!H2:H121,">0",'Денежные потоки'!H2:H121)
A19: Возврат НДС из строительства | B19: руб. | C19: =SUM('Денежные потоки'!G2:G121)
A20: Налог на имущество | B20: руб. | C20: =SUM('Денежные потоки'!K2:K121)
A21: Проценты по кредиту | B21: руб. | C21: =SUM('Денежные потоки'!M2:M121)
A22: СТРУКТУРА ФИНАНСИРОВАНИЯ
A23: Собственные средства | B23: руб. | C23: ='Параметры'!$C$23
A24: Кредит | B24: руб. | C24: ='Параметры'!$C$22
A25: Итого инвестиций | B25: руб. | C25: ='Параметры'!$C$5

Sheet Чувствительность
A1: АНАЛИЗ ЧУВСТВИТЕЛЬНОСТИ
A2: Параметр | B2: Сценарий (пессимист) | C2: Базовый | D2: Сценарий (оптимист) | E2: NPV пессимист | F2: NPV базовый | G2: NPV оптимист
A3: Таблица заполняется командой /sensitivity <name>. Для пересчёта сценариев вручную измените параметры на листе «Параметры».

Sheet Заключение
A1: АНАЛИТИЧЕСКОЕ ЗАКЛЮЧЕНИЕ: Склад Весна
A3: ОПИСАНИЕ ПРОЕКТА
A4: Объект | B4: Склад, площадь 1 000 кв.м.
A5: Дата начала | B5: 01.07.2026
A6: Стоимость | B6: 48 800 000 руб. с НДС
A7: Финансирование | B7: СС 20% / Кредит 80%
A8: Аренда | B8: 1 191 руб./кв.м./мес. с НДС
A9: Срок строительства | B9: 6 мес.
A10: Горизонт | B10: 120 мес. (10 лет)
A12: ИНВЕСТИЦИОННАЯ ПРИВЛЕКАТЕЛЬНОСТЬ: НИЗКАЯ — проект не создаёт стоимости
A14: КЛЮЧЕВЫЕ ПОКАЗАТЕЛИ
A15: Показатель | B15: Значение | C15: Оценка
A16: NPV (чистая приведённая стоимость) | B16: -20 431 191 руб. | C16: отрицательный
A17: IRR (внутренняя норма доходности) | B17: — | C17: не определён
A18: ROI (рентабельность СС за горизонт) | B18: 365.3% | C18: высокий
A19: Срок окупаемости | B19: > 120 мес. | C19: не окупается в горизонте
A21: ФИНАНСОВАЯ НАГРУЗКА
A22: Доля налогов в выручке (б/НДС) | B22: 35.3%
A23: Покрытие процентов (ICR ≈ EBIT/Проценты) | B23: 1.70×
A24: Долговая нагрузка (доля кредита, LTV) | B24: 80%
A25: Суммарные проценты по кредиту | B25: 50 701 733 руб.
A26: Суммарная чистая прибыль за горизонт | B26: 35 654 322 руб.
A28: ОСНОВНЫЕ РИСКИ
A29: 1. | B29: Отрицательный NPV — при текущих параметрах проект разрушает стоимость. Без коррекции аренды, себестоимости или сроков ожидаемая доходность ниже стоимости капитала.
A30: 2. | B30: Проект не окупается в горизонте 120 мес. — макрошоки за пределами окна планирования ставят инвестора в неопределённость.
A31: 3. | B31: Проценты по кредиту (142% от чистой прибыли за горизонт) съедают значительную часть операционного результата.
A32: 4. | B32: Высокая налоговая нагрузка: 35% от выручки идёт в бюджет — проект чувствителен к изменениям налогового режима.
A34: РЕКОМЕНДАЦИИ
A35: • | B35: Пересмотреть базовую экономику: повысить арендную ставку или снизить себестоимость строительства. NPV — самый прямой сигнал нерентабельности.
A36: • | B36: Снизить долю кредита с 80% до 60–65%. Каждые 10 п.п. снижения уменьшают процентную нагрузку и ускоряют окупаемость на 8–15%.
A37: • | B37: Рассмотреть рефинансирование или субсидируемые программы кредитования (например, льготы для промышленных складов) — снижение ставки на 2 п.п. даёт ощутимый прирост IRR.
A39: ВЫВОД
A40: Проект в текущей конфигурации не целесообразен без существенной корректировки параметров. NPV = -20 431 191 руб., IRR = не определён, окупаемость — за пределами горизонта 120 мес.. Перед финальным решением рекомендуется выполнить анализ чувствительности по арендной ставке, себестоимости строительства и кредитной ставке (см. лист «Чувствительность»).
A44: Заключение сгенерировано автоматически на основе KPI и пороговых правил. Для углублённого анализа — см. лист «Чувствительность».
